<?xml version="1.0" ?>
<annotation>
   <folder/>
   <filename>AMP_2012_page_140_table_0.jpg</filename>
   <path>AMP_2012_page_140_table_0.jpg</path>
   <source>
      <database>FinTabNet.c-Structure</database>
   </source>
   <size>
      <width>680</width>
      <height>267</height>
      <depth>3</depth>
   </size>
   <segmented>0</segmented>
   <object>
      <name>table</name>
      <pose>Frontal</pose>
      <truncated>0</truncated>
      <difficult>0</difficult>
      <occluded>0</occluded>
      <bndbox>
         <xmin>28.6434</xmin>
         <ymin>28.6938</ymin>
         <xmax>648.8163</xmax>
         <ymax>236.3579</ymax>
      </bndbox>
   </object>
   <object>
      <name>table spanning cell</name>
      <pose>Frontal</pose>
      <truncated>0</truncated>
      <difficult>0</difficult>
      <occluded>0</occluded>
      <bndbox>
         <xmin>28.6434</xmin>
         <ymin>28.6938</ymin>
         <xmax>161.7080</xmax>
         <ymax>102.2184</ymax>
      </bndbox>
   </object>
   <object>
      <name>table spanning cell</name>
      <pose>Frontal</pose>
      <truncated>0</truncated>
      <difficult>0</difficult>
      <occluded>0</occluded>
      <bndbox>
         <xmin>161.7080</xmin>
         <ymin>28.6938</ymin>
         <xmax>648.8163</xmax>
         <ymax>43.0895</ymax>
      </bndbox>
   </object>
   <object>
      <name>table spanning cell</name>
      <pose>Frontal</pose>
      <truncated>0</truncated>
      <difficult>0</difficult>
      <occluded>0</occluded>
      <bndbox>
         <xmin>161.7080</xmin>
         <ymin>43.0895</ymin>
         <xmax>325.9637</xmax>
         <ymax>59.6267</ymax>
      </bndbox>
   </object>
   <object>
      <name>table spanning cell</name>
      <pose>Frontal</pose>
      <truncated>0</truncated>
      <difficult>0</difficult>
      <occluded>0</occluded>
      <bndbox>
         <xmin>325.9637</xmin>
         <ymin>43.0895</ymin>
         <xmax>489.3243</xmax>
         <ymax>59.6267</ymax>
      </bndbox>
   </object>
   <object>
      <name>table spanning cell</name>
      <pose>Frontal</pose>
      <truncated>0</truncated>
      <difficult>0</difficult>
      <occluded>0</occluded>
      <bndbox>
         <xmin>489.3243</xmin>
         <ymin>43.0895</ymin>
         <xmax>648.8163</xmax>
         <ymax>59.6267</ymax>
      </bndbox>
   </object>
   <object>
      <name>table spanning cell</name>
      <pose>Frontal</pose>
      <truncated>0</truncated>
      <difficult>0</difficult>
      <occluded>0</occluded>
      <bndbox>
         <xmin>161.7080</xmin>
         <ymin>87.5334</ymin>
         <xmax>648.8163</xmax>
         <ymax>102.2184</ymax>
      </bndbox>
   </object>
   <object>
      <name>table column header</name>
      <pose>Frontal</pose>
      <truncated>0</truncated>
      <difficult>0</difficult>
      <occluded>0</occluded>
      <bndbox>
         <xmin>28.6434</xmin>
         <ymin>28.6938</ymin>
         <xmax>648.8163</xmax>
         <ymax>102.2184</ymax>
      </bndbox>
   </object>
   <object>
      <name>table row</name>
      <pose>Frontal</pose>
      <truncated>0</truncated>
      <difficult>0</difficult>
      <occluded>0</occluded>
      <bndbox>
         <xmin>28.6434</xmin>
         <ymin>28.6938</ymin>
         <xmax>648.8163</xmax>
         <ymax>43.0895</ymax>
      </bndbox>
   </object>
   <object>
      <name>table row</name>
      <pose>Frontal</pose>
      <truncated>0</truncated>
      <difficult>0</difficult>
      <occluded>0</occluded>
      <bndbox>
         <xmin>28.6434</xmin>
         <ymin>43.0895</ymin>
         <xmax>648.8163</xmax>
         <ymax>59.6267</ymax>
      </bndbox>
   </object>
   <object>
      <name>table row</name>
      <pose>Frontal</pose>
      <truncated>0</truncated>
      <difficult>0</difficult>
      <occluded>0</occluded>
      <bndbox>
         <xmin>28.6434</xmin>
         <ymin>59.6267</ymin>
         <xmax>648.8163</xmax>
         <ymax>87.5334</ymax>
      </bndbox>
   </object>
   <object>
      <name>table row</name>
      <pose>Frontal</pose>
      <truncated>0</truncated>
      <difficult>0</difficult>
      <occluded>0</occluded>
      <bndbox>
         <xmin>28.6434</xmin>
         <ymin>87.5334</ymin>
         <xmax>648.8163</xmax>
         <ymax>102.2184</ymax>
      </bndbox>
   </object>
   <object>
      <name>table row</name>
      <pose>Frontal</pose>
      <truncated>0</truncated>
      <difficult>0</difficult>
      <occluded>0</occluded>
      <bndbox>
         <xmin>28.6434</xmin>
         <ymin>102.2184</ymin>
         <xmax>648.8163</xmax>
         <ymax>114.5232</ymax>
      </bndbox>
   </object>
   <object>
      <name>table row</name>
      <pose>Frontal</pose>
      <truncated>0</truncated>
      <difficult>0</difficult>
      <occluded>0</occluded>
      <bndbox>
         <xmin>28.6434</xmin>
         <ymin>114.5232</ymin>
         <xmax>648.8163</xmax>
         <ymax>137.7791</ymax>
      </bndbox>
   </object>
   <object>
      <name>table row</name>
      <pose>Frontal</pose>
      <truncated>0</truncated>
      <difficult>0</difficult>
      <occluded>0</occluded>
      <bndbox>
         <xmin>28.6434</xmin>
         <ymin>137.7791</ymin>
         <xmax>648.8163</xmax>
         <ymax>161.0349</ymax>
      </bndbox>
   </object>
   <object>
      <name>table row</name>
      <pose>Frontal</pose>
      <truncated>0</truncated>
      <difficult>0</difficult>
      <occluded>0</occluded>
      <bndbox>
         <xmin>28.6434</xmin>
         <ymin>161.0349</ymin>
         <xmax>648.8163</xmax>
         <ymax>172.6628</ymax>
      </bndbox>
   </object>
   <object>
      <name>table row</name>
      <pose>Frontal</pose>
      <truncated>0</truncated>
      <difficult>0</difficult>
      <occluded>0</occluded>
      <bndbox>
         <xmin>28.6434</xmin>
         <ymin>172.6628</ymin>
         <xmax>648.8163</xmax>
         <ymax>195.9186</ymax>
      </bndbox>
   </object>
   <object>
      <name>table row</name>
      <pose>Frontal</pose>
      <truncated>0</truncated>
      <difficult>0</difficult>
      <occluded>0</occluded>
      <bndbox>
         <xmin>28.6434</xmin>
         <ymin>195.9186</ymin>
         <xmax>648.8163</xmax>
         <ymax>221.7584</ymax>
      </bndbox>
   </object>
   <object>
      <name>table row</name>
      <pose>Frontal</pose>
      <truncated>0</truncated>
      <difficult>0</difficult>
      <occluded>0</occluded>
      <bndbox>
         <xmin>28.6434</xmin>
         <ymin>221.7584</ymin>
         <xmax>648.8163</xmax>
         <ymax>236.3579</ymax>
      </bndbox>
   </object>
   <object>
      <name>table column</name>
      <pose>Frontal</pose>
      <truncated>0</truncated>
      <difficult>0</difficult>
      <occluded>0</occluded>
      <bndbox>
         <xmin>28.6434</xmin>
         <ymin>28.6938</ymin>
         <xmax>161.7080</xmax>
         <ymax>236.3579</ymax>
      </bndbox>
   </object>
   <object>
      <name>table column</name>
      <pose>Frontal</pose>
      <truncated>0</truncated>
      <difficult>0</difficult>
      <occluded>0</occluded>
      <bndbox>
         <xmin>161.7080</xmin>
         <ymin>28.6938</ymin>
         <xmax>219.7362</xmax>
         <ymax>236.3579</ymax>
      </bndbox>
   </object>
   <object>
      <name>table column</name>
      <pose>Frontal</pose>
      <truncated>0</truncated>
      <difficult>0</difficult>
      <occluded>0</occluded>
      <bndbox>
         <xmin>219.7362</xmin>
         <ymin>28.6938</ymin>
         <xmax>269.1712</xmax>
         <ymax>236.3579</ymax>
      </bndbox>
   </object>
   <object>
      <name>table column</name>
      <pose>Frontal</pose>
      <truncated>0</truncated>
      <difficult>0</difficult>
      <occluded>0</occluded>
      <bndbox>
         <xmin>269.1712</xmin>
         <ymin>28.6938</ymin>
         <xmax>325.9637</xmax>
         <ymax>236.3579</ymax>
      </bndbox>
   </object>
   <object>
      <name>table column</name>
      <pose>Frontal</pose>
      <truncated>0</truncated>
      <difficult>0</difficult>
      <occluded>0</occluded>
      <bndbox>
         <xmin>325.9637</xmin>
         <ymin>28.6938</ymin>
         <xmax>383.0915</xmax>
         <ymax>236.3579</ymax>
      </bndbox>
   </object>
   <object>
      <name>table column</name>
      <pose>Frontal</pose>
      <truncated>0</truncated>
      <difficult>0</difficult>
      <occluded>0</occluded>
      <bndbox>
         <xmin>383.0915</xmin>
         <ymin>28.6938</ymin>
         <xmax>432.5312</xmax>
         <ymax>236.3579</ymax>
      </bndbox>
   </object>
   <object>
      <name>table column</name>
      <pose>Frontal</pose>
      <truncated>0</truncated>
      <difficult>0</difficult>
      <occluded>0</occluded>
      <bndbox>
         <xmin>432.5312</xmin>
         <ymin>28.6938</ymin>
         <xmax>489.3243</xmax>
         <ymax>236.3579</ymax>
      </bndbox>
   </object>
   <object>
      <name>table column</name>
      <pose>Frontal</pose>
      <truncated>0</truncated>
      <difficult>0</difficult>
      <occluded>0</occluded>
      <bndbox>
         <xmin>489.3243</xmin>
         <ymin>28.6938</ymin>
         <xmax>546.4566</xmax>
         <ymax>236.3579</ymax>
      </bndbox>
   </object>
   <object>
      <name>table column</name>
      <pose>Frontal</pose>
      <truncated>0</truncated>
      <difficult>0</difficult>
      <occluded>0</occluded>
      <bndbox>
         <xmin>546.4566</xmin>
         <ymin>28.6938</ymin>
         <xmax>595.8916</xmax>
         <ymax>236.3579</ymax>
      </bndbox>
   </object>
   <object>
      <name>table column</name>
      <pose>Frontal</pose>
      <truncated>0</truncated>
      <difficult>0</difficult>
      <occluded>0</occluded>
      <bndbox>
         <xmin>595.8916</xmin>
         <ymin>28.6938</ymin>
         <xmax>648.8163</xmax>
         <ymax>236.3579</ymax>
      </bndbox>
   </object>
</annotation>
