<?xml version="1.0" ?>
<annotation>
   <folder/>
   <filename>ETN_2017_page_85_table_0.jpg</filename>
   <path>ETN_2017_page_85_table_0.jpg</path>
   <source>
      <database>FinTabNet.c-Structure</database>
   </source>
   <size>
      <width>703</width>
      <height>276</height>
      <depth>3</depth>
   </size>
   <segmented>0</segmented>
   <object>
      <name>table</name>
      <pose>Frontal</pose>
      <truncated>0</truncated>
      <difficult>0</difficult>
      <occluded>0</occluded>
      <bndbox>
         <xmin>29.2879</xmin>
         <ymin>28.8977</ymin>
         <xmax>671.9646</xmax>
         <ymax>244.9109</ymax>
      </bndbox>
   </object>
   <object>
      <name>table projected row header</name>
      <pose>Frontal</pose>
      <truncated>0</truncated>
      <difficult>0</difficult>
      <occluded>0</occluded>
      <bndbox>
         <xmin>29.2879</xmin>
         <ymin>181.0962</ymin>
         <xmax>671.9646</xmax>
         <ymax>209.5001</ymax>
      </bndbox>
   </object>
   <object>
      <name>table column header</name>
      <pose>Frontal</pose>
      <truncated>0</truncated>
      <difficult>0</difficult>
      <occluded>0</occluded>
      <bndbox>
         <xmin>29.2879</xmin>
         <ymin>28.8977</ymin>
         <xmax>671.9646</xmax>
         <ymax>57.9849</ymax>
      </bndbox>
   </object>
   <object>
      <name>table row</name>
      <pose>Frontal</pose>
      <truncated>0</truncated>
      <difficult>0</difficult>
      <occluded>0</occluded>
      <bndbox>
         <xmin>29.2879</xmin>
         <ymin>28.8977</ymin>
         <xmax>671.9646</xmax>
         <ymax>57.9849</ymax>
      </bndbox>
   </object>
   <object>
      <name>table row</name>
      <pose>Frontal</pose>
      <truncated>0</truncated>
      <difficult>0</difficult>
      <occluded>0</occluded>
      <bndbox>
         <xmin>29.2879</xmin>
         <ymin>57.9849</ymin>
         <xmax>671.9646</xmax>
         <ymax>86.3992</ymax>
      </bndbox>
   </object>
   <object>
      <name>table row</name>
      <pose>Frontal</pose>
      <truncated>0</truncated>
      <difficult>0</difficult>
      <occluded>0</occluded>
      <bndbox>
         <xmin>29.2879</xmin>
         <ymin>86.3992</ymin>
         <xmax>671.9646</xmax>
         <ymax>114.8083</ymax>
      </bndbox>
   </object>
   <object>
      <name>table row</name>
      <pose>Frontal</pose>
      <truncated>0</truncated>
      <difficult>0</difficult>
      <occluded>0</occluded>
      <bndbox>
         <xmin>29.2879</xmin>
         <ymin>114.8083</ymin>
         <xmax>671.9646</xmax>
         <ymax>143.2174</ymax>
      </bndbox>
   </object>
   <object>
      <name>table row</name>
      <pose>Frontal</pose>
      <truncated>0</truncated>
      <difficult>0</difficult>
      <occluded>0</occluded>
      <bndbox>
         <xmin>29.2879</xmin>
         <ymin>143.2174</ymin>
         <xmax>671.9646</xmax>
         <ymax>181.0962</ymax>
      </bndbox>
   </object>
   <object>
      <name>table row</name>
      <pose>Frontal</pose>
      <truncated>0</truncated>
      <difficult>0</difficult>
      <occluded>0</occluded>
      <bndbox>
         <xmin>29.2879</xmin>
         <ymin>181.0962</ymin>
         <xmax>671.9646</xmax>
         <ymax>209.5001</ymax>
      </bndbox>
   </object>
   <object>
      <name>table row</name>
      <pose>Frontal</pose>
      <truncated>0</truncated>
      <difficult>0</difficult>
      <occluded>0</occluded>
      <bndbox>
         <xmin>29.2879</xmin>
         <ymin>209.5001</ymin>
         <xmax>671.9646</xmax>
         <ymax>228.4447</ymax>
      </bndbox>
   </object>
   <object>
      <name>table row</name>
      <pose>Frontal</pose>
      <truncated>0</truncated>
      <difficult>0</difficult>
      <occluded>0</occluded>
      <bndbox>
         <xmin>29.2879</xmin>
         <ymin>228.4447</ymin>
         <xmax>671.9646</xmax>
         <ymax>244.9109</ymax>
      </bndbox>
   </object>
   <object>
      <name>table column</name>
      <pose>Frontal</pose>
      <truncated>0</truncated>
      <difficult>0</difficult>
      <occluded>0</occluded>
      <bndbox>
         <xmin>29.2879</xmin>
         <ymin>28.8977</ymin>
         <xmax>263.1016</xmax>
         <ymax>244.9109</ymax>
      </bndbox>
   </object>
   <object>
      <name>table column</name>
      <pose>Frontal</pose>
      <truncated>0</truncated>
      <difficult>0</difficult>
      <occluded>0</occluded>
      <bndbox>
         <xmin>263.1016</xmin>
         <ymin>28.8977</ymin>
         <xmax>403.0447</xmax>
         <ymax>244.9109</ymax>
      </bndbox>
   </object>
   <object>
      <name>table column</name>
      <pose>Frontal</pose>
      <truncated>0</truncated>
      <difficult>0</difficult>
      <occluded>0</occluded>
      <bndbox>
         <xmin>403.0447</xmin>
         <ymin>28.8977</ymin>
         <xmax>470.5757</xmax>
         <ymax>244.9109</ymax>
      </bndbox>
   </object>
   <object>
      <name>table column</name>
      <pose>Frontal</pose>
      <truncated>0</truncated>
      <difficult>0</difficult>
      <occluded>0</occluded>
      <bndbox>
         <xmin>470.5757</xmin>
         <ymin>28.8977</ymin>
         <xmax>540.0396</xmax>
         <ymax>244.9109</ymax>
      </bndbox>
   </object>
   <object>
      <name>table column</name>
      <pose>Frontal</pose>
      <truncated>0</truncated>
      <difficult>0</difficult>
      <occluded>0</occluded>
      <bndbox>
         <xmin>540.0396</xmin>
         <ymin>28.8977</ymin>
         <xmax>608.2020</xmax>
         <ymax>244.9109</ymax>
      </bndbox>
   </object>
   <object>
      <name>table column</name>
      <pose>Frontal</pose>
      <truncated>0</truncated>
      <difficult>0</difficult>
      <occluded>0</occluded>
      <bndbox>
         <xmin>608.2020</xmin>
         <ymin>28.8977</ymin>
         <xmax>671.9646</xmax>
         <ymax>244.9109</ymax>
      </bndbox>
   </object>
</annotation>
