<?xml version="1.0" ?>
<annotation>
   <folder/>
   <filename>PEAK_2014_page_119_table_0.jpg</filename>
   <path>PEAK_2014_page_119_table_0.jpg</path>
   <source>
      <database>FinTabNet.c-Structure</database>
   </source>
   <size>
      <width>649</width>
      <height>202</height>
      <depth>3</depth>
   </size>
   <segmented>0</segmented>
   <object>
      <name>table</name>
      <pose>Frontal</pose>
      <truncated>0</truncated>
      <difficult>0</difficult>
      <occluded>0</occluded>
      <bndbox>
         <xmin>29.1473</xmin>
         <ymin>29.1020</ymin>
         <xmax>618.2946</xmax>
         <ymax>171.3966</ymax>
      </bndbox>
   </object>
   <object>
      <name>table column header</name>
      <pose>Frontal</pose>
      <truncated>0</truncated>
      <difficult>0</difficult>
      <occluded>0</occluded>
      <bndbox>
         <xmin>29.1473</xmin>
         <ymin>29.1020</ymin>
         <xmax>618.2946</xmax>
         <ymax>54.4770</ymax>
      </bndbox>
   </object>
   <object>
      <name>table row</name>
      <pose>Frontal</pose>
      <truncated>0</truncated>
      <difficult>0</difficult>
      <occluded>0</occluded>
      <bndbox>
         <xmin>29.1473</xmin>
         <ymin>29.1020</ymin>
         <xmax>618.2946</xmax>
         <ymax>54.4770</ymax>
      </bndbox>
   </object>
   <object>
      <name>table row</name>
      <pose>Frontal</pose>
      <truncated>0</truncated>
      <difficult>0</difficult>
      <occluded>0</occluded>
      <bndbox>
         <xmin>29.1473</xmin>
         <ymin>54.4770</ymin>
         <xmax>618.2946</xmax>
         <ymax>73.0827</ymax>
      </bndbox>
   </object>
   <object>
      <name>table row</name>
      <pose>Frontal</pose>
      <truncated>0</truncated>
      <difficult>0</difficult>
      <occluded>0</occluded>
      <bndbox>
         <xmin>29.1473</xmin>
         <ymin>73.0827</ymin>
         <xmax>618.2946</xmax>
         <ymax>88.5865</ymax>
      </bndbox>
   </object>
   <object>
      <name>table row</name>
      <pose>Frontal</pose>
      <truncated>0</truncated>
      <difficult>0</difficult>
      <occluded>0</occluded>
      <bndbox>
         <xmin>29.1473</xmin>
         <ymin>88.5865</ymin>
         <xmax>618.2946</xmax>
         <ymax>104.0904</ymax>
      </bndbox>
   </object>
   <object>
      <name>table row</name>
      <pose>Frontal</pose>
      <truncated>0</truncated>
      <difficult>0</difficult>
      <occluded>0</occluded>
      <bndbox>
         <xmin>29.1473</xmin>
         <ymin>104.0904</ymin>
         <xmax>618.2946</xmax>
         <ymax>119.5943</ymax>
      </bndbox>
   </object>
   <object>
      <name>table row</name>
      <pose>Frontal</pose>
      <truncated>0</truncated>
      <difficult>0</difficult>
      <occluded>0</occluded>
      <bndbox>
         <xmin>29.1473</xmin>
         <ymin>119.5943</ymin>
         <xmax>618.2946</xmax>
         <ymax>135.0982</ymax>
      </bndbox>
   </object>
   <object>
      <name>table row</name>
      <pose>Frontal</pose>
      <truncated>0</truncated>
      <difficult>0</difficult>
      <occluded>0</occluded>
      <bndbox>
         <xmin>29.1473</xmin>
         <ymin>135.0982</ymin>
         <xmax>618.2946</xmax>
         <ymax>153.1860</ymax>
      </bndbox>
   </object>
   <object>
      <name>table row</name>
      <pose>Frontal</pose>
      <truncated>0</truncated>
      <difficult>0</difficult>
      <occluded>0</occluded>
      <bndbox>
         <xmin>29.1473</xmin>
         <ymin>153.1860</ymin>
         <xmax>618.2946</xmax>
         <ymax>171.3966</ymax>
      </bndbox>
   </object>
   <object>
      <name>table column</name>
      <pose>Frontal</pose>
      <truncated>0</truncated>
      <difficult>0</difficult>
      <occluded>0</occluded>
      <bndbox>
         <xmin>29.1473</xmin>
         <ymin>29.1020</ymin>
         <xmax>294.2184</xmax>
         <ymax>171.3966</ymax>
      </bndbox>
   </object>
   <object>
      <name>table column</name>
      <pose>Frontal</pose>
      <truncated>0</truncated>
      <difficult>0</difficult>
      <occluded>0</occluded>
      <bndbox>
         <xmin>294.2184</xmin>
         <ymin>29.1020</ymin>
         <xmax>561.9700</xmax>
         <ymax>171.3966</ymax>
      </bndbox>
   </object>
   <object>
      <name>table column</name>
      <pose>Frontal</pose>
      <truncated>0</truncated>
      <difficult>0</difficult>
      <occluded>0</occluded>
      <bndbox>
         <xmin>561.9700</xmin>
         <ymin>29.1020</ymin>
         <xmax>618.2946</xmax>
         <ymax>171.3966</ymax>
      </bndbox>
   </object>
</annotation>
