<?xml version="1.0" ?>
<annotation>
   <folder/>
   <filename>PNC_2015_page_226_table_0.jpg</filename>
   <path>PNC_2015_page_226_table_0.jpg</path>
   <source>
      <database>FinTabNet.c-Structure</database>
   </source>
   <size>
      <width>729</width>
      <height>161</height>
      <depth>3</depth>
   </size>
   <segmented>0</segmented>
   <object>
      <name>table</name>
      <pose>Frontal</pose>
      <truncated>0</truncated>
      <difficult>0</difficult>
      <occluded>0</occluded>
      <bndbox>
         <xmin>28.6357</xmin>
         <ymin>28.9289</ymin>
         <xmax>697.8971</xmax>
         <ymax>130.0346</ymax>
      </bndbox>
   </object>
   <object>
      <name>table projected row header</name>
      <pose>Frontal</pose>
      <truncated>0</truncated>
      <difficult>0</difficult>
      <occluded>0</occluded>
      <bndbox>
         <xmin>28.6357</xmin>
         <ymin>78.0381</ymin>
         <xmax>697.8971</xmax>
         <ymax>96.2277</ymax>
      </bndbox>
   </object>
   <object>
      <name>table column header</name>
      <pose>Frontal</pose>
      <truncated>0</truncated>
      <difficult>0</difficult>
      <occluded>0</occluded>
      <bndbox>
         <xmin>28.6357</xmin>
         <ymin>28.9289</ymin>
         <xmax>697.8971</xmax>
         <ymax>78.0381</ymax>
      </bndbox>
   </object>
   <object>
      <name>table row</name>
      <pose>Frontal</pose>
      <truncated>0</truncated>
      <difficult>0</difficult>
      <occluded>0</occluded>
      <bndbox>
         <xmin>28.6357</xmin>
         <ymin>28.9289</ymin>
         <xmax>697.8971</xmax>
         <ymax>78.0381</ymax>
      </bndbox>
   </object>
   <object>
      <name>table row</name>
      <pose>Frontal</pose>
      <truncated>0</truncated>
      <difficult>0</difficult>
      <occluded>0</occluded>
      <bndbox>
         <xmin>28.6357</xmin>
         <ymin>78.0381</ymin>
         <xmax>697.8971</xmax>
         <ymax>96.2277</ymax>
      </bndbox>
   </object>
   <object>
      <name>table row</name>
      <pose>Frontal</pose>
      <truncated>0</truncated>
      <difficult>0</difficult>
      <occluded>0</occluded>
      <bndbox>
         <xmin>28.6357</xmin>
         <ymin>96.2277</ymin>
         <xmax>697.8971</xmax>
         <ymax>114.4962</ymax>
      </bndbox>
   </object>
   <object>
      <name>table row</name>
      <pose>Frontal</pose>
      <truncated>0</truncated>
      <difficult>0</difficult>
      <occluded>0</occluded>
      <bndbox>
         <xmin>28.6357</xmin>
         <ymin>114.4962</ymin>
         <xmax>697.8971</xmax>
         <ymax>130.0346</ymax>
      </bndbox>
   </object>
   <object>
      <name>table column</name>
      <pose>Frontal</pose>
      <truncated>0</truncated>
      <difficult>0</difficult>
      <occluded>0</occluded>
      <bndbox>
         <xmin>28.6357</xmin>
         <ymin>28.9289</ymin>
         <xmax>244.3009</xmax>
         <ymax>130.0346</ymax>
      </bndbox>
   </object>
   <object>
      <name>table column</name>
      <pose>Frontal</pose>
      <truncated>0</truncated>
      <difficult>0</difficult>
      <occluded>0</occluded>
      <bndbox>
         <xmin>244.3009</xmin>
         <ymin>28.9289</ymin>
         <xmax>404.5158</xmax>
         <ymax>130.0346</ymax>
      </bndbox>
   </object>
   <object>
      <name>table column</name>
      <pose>Frontal</pose>
      <truncated>0</truncated>
      <difficult>0</difficult>
      <occluded>0</occluded>
      <bndbox>
         <xmin>404.5158</xmin>
         <ymin>28.9289</ymin>
         <xmax>475.3071</xmax>
         <ymax>130.0346</ymax>
      </bndbox>
   </object>
   <object>
      <name>table column</name>
      <pose>Frontal</pose>
      <truncated>0</truncated>
      <difficult>0</difficult>
      <occluded>0</occluded>
      <bndbox>
         <xmin>475.3071</xmin>
         <ymin>28.9289</ymin>
         <xmax>557.1646</xmax>
         <ymax>130.0346</ymax>
      </bndbox>
   </object>
   <object>
      <name>table column</name>
      <pose>Frontal</pose>
      <truncated>0</truncated>
      <difficult>0</difficult>
      <occluded>0</occluded>
      <bndbox>
         <xmin>557.1646</xmin>
         <ymin>28.9289</ymin>
         <xmax>639.4942</xmax>
         <ymax>130.0346</ymax>
      </bndbox>
   </object>
   <object>
      <name>table column</name>
      <pose>Frontal</pose>
      <truncated>0</truncated>
      <difficult>0</difficult>
      <occluded>0</occluded>
      <bndbox>
         <xmin>639.4942</xmin>
         <ymin>28.9289</ymin>
         <xmax>697.8971</xmax>
         <ymax>130.0346</ymax>
      </bndbox>
   </object>
</annotation>
