<?xml version="1.0" ?>
<annotation>
   <folder/>
   <filename>STT_2014_page_188_table_0.jpg</filename>
   <path>STT_2014_page_188_table_0.jpg</path>
   <source>
      <database>FinTabNet.c-Structure</database>
   </source>
   <size>
      <width>711</width>
      <height>316</height>
      <depth>3</depth>
   </size>
   <segmented>0</segmented>
   <object>
      <name>table</name>
      <pose>Frontal</pose>
      <truncated>0</truncated>
      <difficult>0</difficult>
      <occluded>0</occluded>
      <bndbox>
         <xmin>29.3004</xmin>
         <ymin>29.4093</ymin>
         <xmax>680.2030</xmax>
         <ymax>284.9076</ymax>
      </bndbox>
   </object>
   <object>
      <name>table spanning cell</name>
      <pose>Frontal</pose>
      <truncated>0</truncated>
      <difficult>0</difficult>
      <occluded>0</occluded>
      <bndbox>
         <xmin>29.3004</xmin>
         <ymin>29.4093</ymin>
         <xmax>181.6299</xmax>
         <ymax>102.2145</ymax>
      </bndbox>
   </object>
   <object>
      <name>table spanning cell</name>
      <pose>Frontal</pose>
      <truncated>0</truncated>
      <difficult>0</difficult>
      <occluded>0</occluded>
      <bndbox>
         <xmin>181.6299</xmin>
         <ymin>29.4093</ymin>
         <xmax>438.4022</xmax>
         <ymax>44.7913</ymax>
      </bndbox>
   </object>
   <object>
      <name>table spanning cell</name>
      <pose>Frontal</pose>
      <truncated>0</truncated>
      <difficult>0</difficult>
      <occluded>0</occluded>
      <bndbox>
         <xmin>438.4022</xmin>
         <ymin>29.4093</ymin>
         <xmax>680.2030</xmax>
         <ymax>44.7913</ymax>
      </bndbox>
   </object>
   <object>
      <name>table projected row header</name>
      <pose>Frontal</pose>
      <truncated>0</truncated>
      <difficult>0</difficult>
      <occluded>0</occluded>
      <bndbox>
         <xmin>29.3004</xmin>
         <ymin>102.2145</ymin>
         <xmax>680.2030</xmax>
         <ymax>120.1214</ymax>
      </bndbox>
   </object>
   <object>
      <name>table projected row header</name>
      <pose>Frontal</pose>
      <truncated>0</truncated>
      <difficult>0</difficult>
      <occluded>0</occluded>
      <bndbox>
         <xmin>29.3004</xmin>
         <ymin>210.8030</ymin>
         <xmax>680.2030</xmax>
         <ymax>228.6841</ymax>
      </bndbox>
   </object>
   <object>
      <name>table column header</name>
      <pose>Frontal</pose>
      <truncated>0</truncated>
      <difficult>0</difficult>
      <occluded>0</occluded>
      <bndbox>
         <xmin>29.3004</xmin>
         <ymin>29.4093</ymin>
         <xmax>680.2030</xmax>
         <ymax>102.2145</ymax>
      </bndbox>
   </object>
   <object>
      <name>table row</name>
      <pose>Frontal</pose>
      <truncated>0</truncated>
      <difficult>0</difficult>
      <occluded>0</occluded>
      <bndbox>
         <xmin>29.3004</xmin>
         <ymin>29.4093</ymin>
         <xmax>680.2030</xmax>
         <ymax>44.7913</ymax>
      </bndbox>
   </object>
   <object>
      <name>table row</name>
      <pose>Frontal</pose>
      <truncated>0</truncated>
      <difficult>0</difficult>
      <occluded>0</occluded>
      <bndbox>
         <xmin>29.3004</xmin>
         <ymin>44.7913</ymin>
         <xmax>680.2030</xmax>
         <ymax>102.2145</ymax>
      </bndbox>
   </object>
   <object>
      <name>table row</name>
      <pose>Frontal</pose>
      <truncated>0</truncated>
      <difficult>0</difficult>
      <occluded>0</occluded>
      <bndbox>
         <xmin>29.3004</xmin>
         <ymin>102.2145</ymin>
         <xmax>680.2030</xmax>
         <ymax>120.1214</ymax>
      </bndbox>
   </object>
   <object>
      <name>table row</name>
      <pose>Frontal</pose>
      <truncated>0</truncated>
      <difficult>0</difficult>
      <occluded>0</occluded>
      <bndbox>
         <xmin>29.3004</xmin>
         <ymin>120.1214</ymin>
         <xmax>680.2030</xmax>
         <ymax>138.0024</ymax>
      </bndbox>
   </object>
   <object>
      <name>table row</name>
      <pose>Frontal</pose>
      <truncated>0</truncated>
      <difficult>0</difficult>
      <occluded>0</occluded>
      <bndbox>
         <xmin>29.3004</xmin>
         <ymin>138.0024</ymin>
         <xmax>680.2030</xmax>
         <ymax>156.5220</ymax>
      </bndbox>
   </object>
   <object>
      <name>table row</name>
      <pose>Frontal</pose>
      <truncated>0</truncated>
      <difficult>0</difficult>
      <occluded>0</occluded>
      <bndbox>
         <xmin>29.3004</xmin>
         <ymin>156.5220</ymin>
         <xmax>680.2030</xmax>
         <ymax>175.0415</ymax>
      </bndbox>
   </object>
   <object>
      <name>table row</name>
      <pose>Frontal</pose>
      <truncated>0</truncated>
      <difficult>0</difficult>
      <occluded>0</occluded>
      <bndbox>
         <xmin>29.3004</xmin>
         <ymin>175.0415</ymin>
         <xmax>680.2030</xmax>
         <ymax>192.9226</ymax>
      </bndbox>
   </object>
   <object>
      <name>table row</name>
      <pose>Frontal</pose>
      <truncated>0</truncated>
      <difficult>0</difficult>
      <occluded>0</occluded>
      <bndbox>
         <xmin>29.3004</xmin>
         <ymin>192.9226</ymin>
         <xmax>680.2030</xmax>
         <ymax>210.8030</ymax>
      </bndbox>
   </object>
   <object>
      <name>table row</name>
      <pose>Frontal</pose>
      <truncated>0</truncated>
      <difficult>0</difficult>
      <occluded>0</occluded>
      <bndbox>
         <xmin>29.3004</xmin>
         <ymin>210.8030</ymin>
         <xmax>680.2030</xmax>
         <ymax>228.6841</ymax>
      </bndbox>
   </object>
   <object>
      <name>table row</name>
      <pose>Frontal</pose>
      <truncated>0</truncated>
      <difficult>0</difficult>
      <occluded>0</occluded>
      <bndbox>
         <xmin>29.3004</xmin>
         <ymin>228.6841</ymin>
         <xmax>680.2030</xmax>
         <ymax>258.0559</ymax>
      </bndbox>
   </object>
   <object>
      <name>table row</name>
      <pose>Frontal</pose>
      <truncated>0</truncated>
      <difficult>0</difficult>
      <occluded>0</occluded>
      <bndbox>
         <xmin>29.3004</xmin>
         <ymin>258.0559</ymin>
         <xmax>680.2030</xmax>
         <ymax>284.9076</ymax>
      </bndbox>
   </object>
   <object>
      <name>table column</name>
      <pose>Frontal</pose>
      <truncated>0</truncated>
      <difficult>0</difficult>
      <occluded>0</occluded>
      <bndbox>
         <xmin>29.3004</xmin>
         <ymin>29.4093</ymin>
         <xmax>181.6299</xmax>
         <ymax>284.9076</ymax>
      </bndbox>
   </object>
   <object>
      <name>table column</name>
      <pose>Frontal</pose>
      <truncated>0</truncated>
      <difficult>0</difficult>
      <occluded>0</occluded>
      <bndbox>
         <xmin>181.6299</xmin>
         <ymin>29.4093</ymin>
         <xmax>265.5681</xmax>
         <ymax>284.9076</ymax>
      </bndbox>
   </object>
   <object>
      <name>table column</name>
      <pose>Frontal</pose>
      <truncated>0</truncated>
      <difficult>0</difficult>
      <occluded>0</occluded>
      <bndbox>
         <xmin>265.5681</xmin>
         <ymin>29.4093</ymin>
         <xmax>353.0262</xmax>
         <ymax>284.9076</ymax>
      </bndbox>
   </object>
   <object>
      <name>table column</name>
      <pose>Frontal</pose>
      <truncated>0</truncated>
      <difficult>0</difficult>
      <occluded>0</occluded>
      <bndbox>
         <xmin>353.0262</xmin>
         <ymin>29.4093</ymin>
         <xmax>438.4022</xmax>
         <ymax>284.9076</ymax>
      </bndbox>
   </object>
   <object>
      <name>table column</name>
      <pose>Frontal</pose>
      <truncated>0</truncated>
      <difficult>0</difficult>
      <occluded>0</occluded>
      <bndbox>
         <xmin>438.4022</xmin>
         <ymin>29.4093</ymin>
         <xmax>520.7722</xmax>
         <ymax>284.9076</ymax>
      </bndbox>
   </object>
   <object>
      <name>table column</name>
      <pose>Frontal</pose>
      <truncated>0</truncated>
      <difficult>0</difficult>
      <occluded>0</occluded>
      <bndbox>
         <xmin>520.7722</xmin>
         <ymin>29.4093</ymin>
         <xmax>608.2354</xmax>
         <ymax>284.9076</ymax>
      </bndbox>
   </object>
   <object>
      <name>table column</name>
      <pose>Frontal</pose>
      <truncated>0</truncated>
      <difficult>0</difficult>
      <occluded>0</occluded>
      <bndbox>
         <xmin>608.2354</xmin>
         <ymin>29.4093</ymin>
         <xmax>680.2030</xmax>
         <ymax>284.9076</ymax>
      </bndbox>
   </object>
</annotation>
