<?xml version="1.0" ?>
<annotation>
   <folder/>
   <filename>XEL_2009_page_42_table_0.jpg</filename>
   <path>XEL_2009_page_42_table_0.jpg</path>
   <source>
      <database>FinTabNet.c-Structure</database>
   </source>
   <size>
      <width>618</width>
      <height>170</height>
      <depth>3</depth>
   </size>
   <segmented>0</segmented>
   <object>
      <name>table</name>
      <pose>Frontal</pose>
      <truncated>0</truncated>
      <difficult>0</difficult>
      <occluded>0</occluded>
      <bndbox>
         <xmin>28.6512</xmin>
         <ymin>29.2957</ymin>
         <xmax>586.8047</xmax>
         <ymax>139.0059</ymax>
      </bndbox>
   </object>
   <object>
      <name>table column header</name>
      <pose>Frontal</pose>
      <truncated>0</truncated>
      <difficult>0</difficult>
      <occluded>0</occluded>
      <bndbox>
         <xmin>28.6512</xmin>
         <ymin>29.2957</ymin>
         <xmax>586.8047</xmax>
         <ymax>45.0248</ymax>
      </bndbox>
   </object>
   <object>
      <name>table row</name>
      <pose>Frontal</pose>
      <truncated>0</truncated>
      <difficult>0</difficult>
      <occluded>0</occluded>
      <bndbox>
         <xmin>28.6512</xmin>
         <ymin>29.2957</ymin>
         <xmax>586.8047</xmax>
         <ymax>45.0248</ymax>
      </bndbox>
   </object>
   <object>
      <name>table row</name>
      <pose>Frontal</pose>
      <truncated>0</truncated>
      <difficult>0</difficult>
      <occluded>0</occluded>
      <bndbox>
         <xmin>28.6512</xmin>
         <ymin>45.0248</ymin>
         <xmax>586.8047</xmax>
         <ymax>63.3733</ymax>
      </bndbox>
   </object>
   <object>
      <name>table row</name>
      <pose>Frontal</pose>
      <truncated>0</truncated>
      <difficult>0</difficult>
      <occluded>0</occluded>
      <bndbox>
         <xmin>28.6512</xmin>
         <ymin>63.3733</ymin>
         <xmax>586.8047</xmax>
         <ymax>77.5849</ymax>
      </bndbox>
   </object>
   <object>
      <name>table row</name>
      <pose>Frontal</pose>
      <truncated>0</truncated>
      <difficult>0</difficult>
      <occluded>0</occluded>
      <bndbox>
         <xmin>28.6512</xmin>
         <ymin>77.5849</ymin>
         <xmax>586.8047</xmax>
         <ymax>91.7966</ymax>
      </bndbox>
   </object>
   <object>
      <name>table row</name>
      <pose>Frontal</pose>
      <truncated>0</truncated>
      <difficult>0</difficult>
      <occluded>0</occluded>
      <bndbox>
         <xmin>28.6512</xmin>
         <ymin>91.7966</ymin>
         <xmax>586.8047</xmax>
         <ymax>106.0082</ymax>
      </bndbox>
   </object>
   <object>
      <name>table row</name>
      <pose>Frontal</pose>
      <truncated>0</truncated>
      <difficult>0</difficult>
      <occluded>0</occluded>
      <bndbox>
         <xmin>28.6512</xmin>
         <ymin>106.0082</ymin>
         <xmax>586.8047</xmax>
         <ymax>122.8042</ymax>
      </bndbox>
   </object>
   <object>
      <name>table row</name>
      <pose>Frontal</pose>
      <truncated>0</truncated>
      <difficult>0</difficult>
      <occluded>0</occluded>
      <bndbox>
         <xmin>28.6512</xmin>
         <ymin>122.8042</ymin>
         <xmax>586.8047</xmax>
         <ymax>139.0059</ymax>
      </bndbox>
   </object>
   <object>
      <name>table column</name>
      <pose>Frontal</pose>
      <truncated>0</truncated>
      <difficult>0</difficult>
      <occluded>0</occluded>
      <bndbox>
         <xmin>28.6512</xmin>
         <ymin>29.2957</ymin>
         <xmax>324.6059</xmax>
         <ymax>139.0059</ymax>
      </bndbox>
   </object>
   <object>
      <name>table column</name>
      <pose>Frontal</pose>
      <truncated>0</truncated>
      <difficult>0</difficult>
      <occluded>0</occluded>
      <bndbox>
         <xmin>324.6059</xmin>
         <ymin>29.2957</ymin>
         <xmax>547.0821</xmax>
         <ymax>139.0059</ymax>
      </bndbox>
   </object>
   <object>
      <name>table column</name>
      <pose>Frontal</pose>
      <truncated>0</truncated>
      <difficult>0</difficult>
      <occluded>0</occluded>
      <bndbox>
         <xmin>547.0821</xmin>
         <ymin>29.2957</ymin>
         <xmax>586.8047</xmax>
         <ymax>139.0059</ymax>
      </bndbox>
   </object>
</annotation>
