[{"flags": 0, "span_num": 10, "line_num": 0, "block_num": 0, "bbox": [266.91932, 5.200909999999993, 279.6648, 16.813050000000004], "text": "(In"}, {"flags": 0, "span_num": 11, "line_num": 0, "block_num": 0, "bbox": [282.91022, 5.200909999999993, 326.5748, 16.813050000000004], "text": "millions,"}, {"flags": 0, "span_num": 12, "line_num": 0, "block_num": 0, "bbox": [330.08336, 5.200909999999993, 362.32827, 16.813050000000004], "text": "except"}, {"flags": 0, "span_num": 13, "line_num": 0, "block_num": 0, "bbox": [365.26331, 5.200909999999993, 398.22854, 16.813050000000004], "text": "shares"}, {"flags": 0, "span_num": 14, "line_num": 0, "block_num": 0, "bbox": [401.24284, 5.200909999999993, 419.5851, 16.813050000000004], "text": "and"}, {"flags": 0, "span_num": 15, "line_num": 0, "block_num": 0, "bbox": [422.83052, 5.200909999999993, 438.86866, 16.813050000000004], "text": "par"}, {"flags": 0, "span_num": 16, "line_num": 0, "block_num": 0, "bbox": [442.0196, 5.200909999999993, 471.86591, 16.813050000000004], "text": "value)"}, {"flags": 0, "span_num": 17, "line_num": 0, "block_num": 0, "bbox": [618.71896, 28.960289999999986, 658.60948, 37.89269999999999], "text": "December"}, {"flags": 0, "span_num": 18, "line_num": 0, "block_num": 0, "bbox": [661.09489, 28.960289999999986, 672.91082, 37.89269999999999], "text": "31,"}, {"flags": 0, "span_num": 19, "line_num": 0, "block_num": 0, "bbox": [599.52992, 40.156229999999994, 618.3684, 49.08865], "text": "2016"}, {"flags": 0, "span_num": 20, "line_num": 0, "block_num": 0, "bbox": [673.08799, 40.156229999999994, 691.92651, 49.08865], "text": "2015"}, {"flags": 0, "span_num": 21, "line_num": 0, "block_num": 0, "bbox": [29.454549999999998, 49.974819999999994, 71.56728, 61.58697000000001], "text": "ASSETS"}, {"flags": 0, "span_num": 22, "line_num": 0, "block_num": 0, "bbox": [29.454549999999998, 61.96977000000001, 66.49673, 73.58192], "text": "Current"}, {"flags": 0, "span_num": 23, "line_num": 0, "block_num": 0, "bbox": [69.43178, 61.96977000000001, 100.7979, 73.58192], "text": "assets"}, {"flags": 0, "span_num": 24, "line_num": 0, "block_num": 0, "bbox": [42.24726, 73.96472, 66.41748, 85.57687000000001], "text": "Cash"}, {"flags": 0, "span_num": 25, "line_num": 0, "block_num": 0, "bbox": [589.13583, 73.96472, 594.91652, 85.57687000000001], "text": "$"}, {"flags": 0, "span_num": 26, "line_num": 0, "block_num": 0, "bbox": [612.3226, 73.96472, 629.29693, 85.57687000000001], "text": "322"}, {"flags": 0, "span_num": 27, "line_num": 0, "block_num": 0, "bbox": [662.69398, 73.96472, 668.47468, 85.57687000000001], "text": "$"}, {"flags": 0, "span_num": 28, "line_num": 0, "block_num": 0, "bbox": [685.88072, 73.96472, 702.85504, 85.57687000000001], "text": "390"}, {"flags": 0, "span_num": 29, "line_num": 0, "block_num": 0, "bbox": [42.24726, 85.95473999999999, 90.88285, 97.56689], "text": "Short-term"}, {"flags": 0, "span_num": 30, "line_num": 0, "block_num": 0, "bbox": [94.21766, 85.95473999999999, 150.58556, 97.56689], "text": "investments"}, {"flags": 0, "span_num": 31, "line_num": 0, "block_num": 0, "bbox": [603.52764, 85.95473999999999, 629.29693, 97.56689], "text": "6,037"}, {"flags": 0, "span_num": 32, "line_num": 0, "block_num": 0, "bbox": [677.08572, 85.95473999999999, 702.85504, 97.56689], "text": "5,864"}, {"flags": 0, "span_num": 33, "line_num": 0, "block_num": 0, "bbox": [42.24726, 97.94969, 89.60428, 109.56183999999999], "text": "Restricted"}, {"flags": 0, "span_num": 34, "line_num": 0, "block_num": 0, "bbox": [92.61857, 97.94969, 115.18970999999999, 109.56183999999999], "text": "cash"}, {"flags": 0, "span_num": 35, "line_num": 0, "block_num": 0, "bbox": [118.20401000000001, 97.94969, 135.17832, 109.56183999999999], "text": "and"}, {"flags": 0, "span_num": 36, "line_num": 0, "block_num": 0, "bbox": [138.19263, 97.94969, 185.22911, 109.56183999999999], "text": "short-term"}, {"flags": 0, "span_num": 37, "line_num": 0, "block_num": 0, "bbox": [188.56395, 97.94969, 244.93184000000002, 109.56183999999999], "text": "investments"}, {"flags": 0, "span_num": 38, "line_num": 0, "block_num": 0, "bbox": [612.3226, 97.94969, 629.29693, 109.56183999999999], "text": "638"}, {"flags": 0, "span_num": 39, "line_num": 0, "block_num": 0, "bbox": [685.88072, 97.94969, 702.85504, 109.56183999999999], "text": "695"}, {"flags": 0, "span_num": 40, "line_num": 0, "block_num": 0, "bbox": [42.24726, 109.94463999999999, 85.82245, 121.55679], "text": "Accounts"}, {"flags": 0, "span_num": 41, "line_num": 0, "block_num": 0, "bbox": [89.42039, 109.94463999999999, 139.48135, 121.55679], "text": "receivable,"}, {"flags": 0, "span_num": 42, "line_num": 0, "block_num": 0, "bbox": [142.98989, 109.94463999999999, 157.07131, 121.55679], "text": "net"}, {"flags": 0, "span_num": 43, "line_num": 0, "block_num": 0, "bbox": [603.52764, 109.94463999999999, 629.29693, 121.55679], "text": "1,594"}, {"flags": 0, "span_num": 44, "line_num": 0, "block_num": 0, "bbox": [677.08572, 109.94463999999999, 702.85504, 121.55679], "text": "1,425"}, {"flags": 0, "span_num": 45, "line_num": 0, "block_num": 0, "bbox": [42.24726, 121.93465, 75.51778, 133.5468], "text": "Aircraft"}, {"flags": 0, "span_num": 46, "line_num": 0, "block_num": 0, "bbox": [79.02631, 121.93465, 98.70457, 133.5468], "text": "fuel,"}, {"flags": 0, "span_num": 47, "line_num": 0, "block_num": 0, "bbox": [102.21311, 121.93465, 127.98241999999999, 133.5468], "text": "spare"}, {"flags": 0, "span_num": 48, "line_num": 0, "block_num": 0, "bbox": [130.99672, 121.93465, 153.78374, 133.5468], "text": "parts"}, {"flags": 0, "span_num": 49, "line_num": 0, "block_num": 0, "bbox": [157.38169, 121.93465, 174.35601, 133.5468], "text": "and"}, {"flags": 0, "span_num": 50, "line_num": 0, "block_num": 0, "bbox": [177.37032, 121.93465, 218.63627, 133.5468], "text": "supplies,"}, {"flags": 0, "span_num": 51, "line_num": 0, "block_num": 0, "bbox": [222.14481, 121.93465, 236.22624, 133.5468], "text": "net"}, {"flags": 0, "span_num": 52, "line_num": 0, "block_num": 0, "bbox": [603.52764, 121.93465, 629.29693, 133.5468], "text": "1,094"}, {"flags": 0, "span_num": 53, "line_num": 0, "block_num": 0, "bbox": [685.88072, 121.93465, 702.85504, 133.5468], "text": "863"}, {"flags": 0, "span_num": 54, "line_num": 0, "block_num": 0, "bbox": [42.24726, 133.9296, 77.61111, 145.54175], "text": "Prepaid"}, {"flags": 0, "span_num": 55, "line_num": 0, "block_num": 0, "bbox": [80.62541, 133.9296, 125.00013999999999, 145.54175], "text": "expenses"}, {"flags": 0, "span_num": 56, "line_num": 0, "block_num": 0, "bbox": [128.59808, 133.9296, 145.57241, 145.54175], "text": "and"}, {"flags": 0, "span_num": 57, "line_num": 0, "block_num": 0, "bbox": [148.58669, 133.9296, 172.03664, 145.54175], "text": "other"}, {"flags": 0, "span_num": 58, "line_num": 0, "block_num": 0, "bbox": [612.3226, 133.9296, 629.29693, 145.54175], "text": "639"}, {"flags": 0, "span_num": 59, "line_num": 0, "block_num": 0, "bbox": [685.88072, 133.9296, 702.85504, 145.54175], "text": "748"}, {"flags": 0, "span_num": 60, "line_num": 0, "block_num": 0, "bbox": [55.03998, 148.32157, 78.13737, 159.93372], "text": "Total"}, {"flags": 0, "span_num": 61, "line_num": 0, "block_num": 0, "bbox": [81.42495, 148.32157, 113.09638000000001, 159.93372], "text": "current"}, {"flags": 0, "span_num": 62, "line_num": 0, "block_num": 0, "bbox": [116.60491999999999, 148.32157, 147.38738, 159.93372], "text": "assets"}, {"flags": 0, "span_num": 63, "line_num": 0, "block_num": 0, "bbox": [597.93083, 148.32157, 629.29693, 159.93372], "text": "10,324"}, {"flags": 0, "span_num": 64, "line_num": 0, "block_num": 0, "bbox": [677.08572, 148.32157, 702.85504, 159.93372], "text": "9,985"}, {"flags": 0, "span_num": 65, "line_num": 0, "block_num": 0, "bbox": [29.454549999999998, 160.31159000000002, 78.17954, 171.92374], "text": "Operating"}, {"flags": 0, "span_num": 66, "line_num": 0, "block_num": 0, "bbox": [81.42495, 160.31159000000002, 123.18515, 171.92374], "text": "property"}, {"flags": 0, "span_num": 67, "line_num": 0, "block_num": 0, "bbox": [126.19945000000001, 160.31159000000002, 144.54175, 171.92374], "text": "and"}, {"flags": 0, "span_num": 68, "line_num": 0, "block_num": 0, "bbox": [147.78715, 160.31159000000002, 200.82024, 171.92374], "text": "equipment"}, {"flags": 0, "span_num": 69, "line_num": 0, "block_num": 0, "bbox": [42.24726, 172.30653999999998, 67.52232, 183.91869000000003], "text": "Flight"}, {"flags": 0, "span_num": 70, "line_num": 0, "block_num": 0, "bbox": [71.03087, 172.30653999999998, 118.69318000000001, 183.91869000000003], "text": "equipment"}, {"flags": 0, "span_num": 71, "line_num": 0, "block_num": 0, "bbox": [597.93083, 172.30653999999998, 629.29693, 183.91869000000003], "text": "37,028"}, {"flags": 0, "span_num": 72, "line_num": 0, "block_num": 0, "bbox": [671.4889, 172.30653999999998, 702.85504, 183.91869000000003], "text": "33,185"}, {"flags": 0, "span_num": 73, "line_num": 0, "block_num": 0, "bbox": [42.24726, 184.30149, 76.01202, 195.91364], "text": "Ground"}, {"flags": 0, "span_num": 74, "line_num": 0, "block_num": 0, "bbox": [79.02631, 184.30149, 116.20514, 195.91364], "text": "property"}, {"flags": 0, "span_num": 75, "line_num": 0, "block_num": 0, "bbox": [119.8031, 184.30149, 136.77741, 195.91364], "text": "and"}, {"flags": 0, "span_num": 76, "line_num": 0, "block_num": 0, "bbox": [139.79172, 184.30149, 187.45403, 195.91364], "text": "equipment"}, {"flags": 0, "span_num": 77, "line_num": 0, "block_num": 0, "bbox": [603.52764, 184.30149, 629.29693, 195.91364], "text": "7,116"}, {"flags": 0, "span_num": 78, "line_num": 0, "block_num": 0, "bbox": [677.08572, 184.30149, 702.85504, 195.91364], "text": "6,402"}, {"flags": 0, "span_num": 79, "line_num": 0, "block_num": 0, "bbox": [42.24726, 196.29149999999998, 91.50866, 207.90365000000003], "text": "Equipment"}, {"flags": 0, "span_num": 80, "line_num": 0, "block_num": 0, "bbox": [95.01721, 196.29149999999998, 137.57696, 207.90365000000003], "text": "purchase"}, {"flags": 0, "span_num": 81, "line_num": 0, "block_num": 0, "bbox": [140.59125, 196.29149999999998, 179.36918, 207.90365000000003], "text": "deposits"}, {"flags": 0, "span_num": 82, "line_num": 0, "block_num": 0, "bbox": [603.52764, 196.29149999999998, 629.29693, 207.90365000000003], "text": "1,209"}, {"flags": 0, "span_num": 83, "line_num": 0, "block_num": 0, "bbox": [677.08572, 196.29149999999998, 702.85504, 207.90365000000003], "text": "1,067"}, {"flags": 0, "span_num": 84, "line_num": 0, "block_num": 0, "bbox": [55.03998, 210.68347, 78.13737, 222.29561999999999], "text": "Total"}, {"flags": 0, "span_num": 85, "line_num": 0, "block_num": 0, "bbox": [81.42495, 210.68347, 118.60378, 222.29561999999999], "text": "property"}, {"flags": 0, "span_num": 86, "line_num": 0, "block_num": 0, "bbox": [122.20173, 210.68347, 139.17605, 222.29561999999999], "text": "and"}, {"flags": 0, "span_num": 87, "line_num": 0, "block_num": 0, "bbox": [142.19034, 210.68347, 193.05084, 222.29561999999999], "text": "equipment,"}, {"flags": 0, "span_num": 88, "line_num": 0, "block_num": 0, "bbox": [196.55938, 210.68347, 205.044, 222.29561999999999], "text": "at"}, {"flags": 0, "span_num": 89, "line_num": 0, "block_num": 0, "bbox": [208.55256, 210.68347, 228.23079, 222.29561999999999], "text": "cost"}, {"flags": 0, "span_num": 90, "line_num": 0, "block_num": 0, "bbox": [597.93083, 210.68347, 629.29693, 222.29561999999999], "text": "45,353"}, {"flags": 0, "span_num": 91, "line_num": 0, "block_num": 0, "bbox": [671.4889, 210.68347, 702.85504, 222.29561999999999], "text": "40,654"}, {"flags": 0, "span_num": 92, "line_num": 0, "block_num": 0, "bbox": [42.24726, 222.67844000000002, 64.23473, 234.29057], "text": "Less"}, {"flags": 0, "span_num": 93, "line_num": 0, "block_num": 0, "bbox": [67.83269, 222.67844000000002, 127.18288000000001, 234.29057], "text": "accumulated"}, {"flags": 0, "span_num": 94, "line_num": 0, "block_num": 0, "bbox": [130.19717, 222.67844000000002, 186.34919, 234.29057], "text": "depreciation"}, {"flags": 0, "span_num": 95, "line_num": 0, "block_num": 0, "bbox": [189.3635, 222.67844000000002, 206.3378, 234.29057], "text": "and"}, {"flags": 0, "span_num": 96, "line_num": 0, "block_num": 0, "bbox": [209.3521, 222.67844000000002, 266.30365, 234.29057], "text": "amortization"}, {"flags": 0, "span_num": 97, "line_num": 0, "block_num": 0, "bbox": [594.73265, 222.67844000000002, 632.57437, 234.29057], "text": "(14,194)"}, {"flags": 0, "span_num": 98, "line_num": 0, "block_num": 0, "bbox": [668.29072, 222.67844000000002, 706.13244, 234.29057], "text": "(13,144)"}, {"flags": 0, "span_num": 99, "line_num": 0, "block_num": 0, "bbox": [55.03998, 237.07040999999998, 78.13737, 248.68254000000002], "text": "Total"}, {"flags": 0, "span_num": 100, "line_num": 0, "block_num": 0, "bbox": [81.42495, 237.07040999999998, 118.60378, 248.68254000000002], "text": "property"}, {"flags": 0, "span_num": 101, "line_num": 0, "block_num": 0, "bbox": [122.20173, 237.07040999999998, 139.17605, 248.68254000000002], "text": "and"}, {"flags": 0, "span_num": 102, "line_num": 0, "block_num": 0, "bbox": [142.19034, 237.07040999999998, 193.05084, 248.68254000000002], "text": "equipment,"}, {"flags": 0, "span_num": 103, "line_num": 0, "block_num": 0, "bbox": [196.55938, 237.07040999999998, 210.64082, 248.68254000000002], "text": "net"}, {"flags": 0, "span_num": 104, "line_num": 0, "block_num": 0, "bbox": [597.93083, 237.07040999999998, 629.29693, 248.68254000000002], "text": "31,159"}, {"flags": 0, "span_num": 105, "line_num": 0, "block_num": 0, "bbox": [671.4889, 237.07040999999998, 702.85504, 248.68254000000002], "text": "27,510"}, {"flags": 0, "span_num": 106, "line_num": 0, "block_num": 0, "bbox": [29.454549999999998, 249.06536, 56.686310000000006, 260.67749], "text": "Other"}, {"flags": 0, "span_num": 107, "line_num": 0, "block_num": 0, "bbox": [59.837239999999994, 249.06536, 91.20336, 260.67749], "text": "assets"}, {"flags": 0, "span_num": 108, "line_num": 0, "block_num": 0, "bbox": [42.24726, 261.05537, 81.33555, 272.6675], "text": "Goodwill"}, {"flags": 0, "span_num": 109, "line_num": 0, "block_num": 0, "bbox": [603.52764, 261.05537, 629.29693, 272.6675], "text": "4,091"}, {"flags": 0, "span_num": 110, "line_num": 0, "block_num": 0, "bbox": [677.08572, 261.05537, 702.85504, 272.6675], "text": "4,091"}, {"flags": 0, "span_num": 111, "line_num": 0, "block_num": 0, "bbox": [42.24726, 273.05032, 95.50639, 284.66245], "text": "Intangibles,"}, {"flags": 0, "span_num": 112, "line_num": 0, "block_num": 0, "bbox": [99.01493, 273.05032, 113.09638000000001, 284.66245], "text": "net"}, {"flags": 0, "span_num": 113, "line_num": 0, "block_num": 0, "bbox": [116.60491999999999, 273.05032, 125.08955, 284.66245], "text": "of"}, {"flags": 0, "span_num": 114, "line_num": 0, "block_num": 0, "bbox": [128.59808, 273.05032, 187.94828, 284.66245], "text": "accumulated"}, {"flags": 0, "span_num": 115, "line_num": 0, "block_num": 0, "bbox": [190.96259, 273.05032, 247.91413, 284.66245], "text": "amortization"}, {"flags": 0, "span_num": 116, "line_num": 0, "block_num": 0, "bbox": [250.92843, 273.05032, 259.41303, 284.66245], "text": "of"}, {"flags": 0, "span_num": 117, "line_num": 0, "block_num": 0, "bbox": [262.92159, 273.05032, 285.49273, 284.66245], "text": "$578"}, {"flags": 0, "span_num": 118, "line_num": 0, "block_num": 0, "bbox": [288.50701, 273.05032, 305.48134, 284.66245], "text": "and"}, {"flags": 0, "span_num": 119, "line_num": 0, "block_num": 0, "bbox": [308.49564, 273.05032, 333.77071, 284.66245], "text": "$502,"}, {"flags": 0, "span_num": 120, "line_num": 0, "block_num": 0, "bbox": [337.27927, 273.05032, 392.84762, 284.66245], "text": "respectively"}, {"flags": 0, "span_num": 121, "line_num": 0, "block_num": 0, "bbox": [603.52764, 273.05032, 629.29693, 284.66245], "text": "2,173"}, {"flags": 0, "span_num": 122, "line_num": 0, "block_num": 0, "bbox": [677.08572, 273.05032, 702.85504, 284.66245], "text": "2,249"}, {"flags": 0, "span_num": 123, "line_num": 0, "block_num": 0, "bbox": [42.24726, 285.04034, 81.60884, 296.65247], "text": "Deferred"}, {"flags": 0, "span_num": 124, "line_num": 0, "block_num": 0, "bbox": [84.62313, 285.04034, 98.61516, 296.65247], "text": "tax"}, {"flags": 0, "span_num": 125, "line_num": 0, "block_num": 0, "bbox": [102.21311, 285.04034, 127.48817, 296.65247], "text": "asset"}, {"flags": 0, "span_num": 126, "line_num": 0, "block_num": 0, "bbox": [603.52764, 285.04034, 629.29693, 296.65247], "text": "1,498"}, {"flags": 0, "span_num": 127, "line_num": 0, "block_num": 0, "bbox": [677.08572, 285.04034, 702.85504, 296.65247], "text": "2,477"}, {"flags": 0, "span_num": 128, "line_num": 0, "block_num": 0, "bbox": [42.24726, 297.03529, 68.09582, 308.64742], "text": "Other"}, {"flags": 0, "span_num": 129, "line_num": 0, "block_num": 0, "bbox": [71.03087, 297.03529, 101.81334, 308.64742], "text": "assets"}, {"flags": 0, "span_num": 130, "line_num": 0, "block_num": 0, "bbox": [603.52764, 297.03529, 629.29693, 308.64742], "text": "2,029"}, {"flags": 0, "span_num": 131, "line_num": 0, "block_num": 0, "bbox": [677.08572, 297.03529, 702.85504, 308.64742], "text": "2,103"}, {"flags": 0, "span_num": 132, "line_num": 0, "block_num": 0, "bbox": [55.03998, 311.42726, 78.13737, 323.03939], "text": "Total"}, {"flags": 0, "span_num": 133, "line_num": 0, "block_num": 0, "bbox": [81.42495, 311.42726, 104.87488, 323.03939], "text": "other"}, {"flags": 0, "span_num": 134, "line_num": 0, "block_num": 0, "bbox": [107.80993, 311.42726, 138.5924, 323.03939], "text": "assets"}, {"flags": 0, "span_num": 135, "line_num": 0, "block_num": 0, "bbox": [603.52764, 311.42726, 629.29693, 323.03939], "text": "9,791"}, {"flags": 0, "span_num": 136, "line_num": 0, "block_num": 0, "bbox": [671.4889, 311.42726, 702.85504, 323.03939], "text": "10,920"}, {"flags": 0, "span_num": 137, "line_num": 0, "block_num": 0, "bbox": [67.83269, 325.81922, 92.3082, 337.43135], "text": "Total"}, {"flags": 0, "span_num": 138, "line_num": 0, "block_num": 0, "bbox": [95.81675, 325.81922, 127.18288000000001, 337.43135], "text": "assets"}, {"flags": 0, "span_num": 139, "line_num": 0, "block_num": 0, "bbox": [589.13583, 325.81922, 594.91652, 337.43135], "text": "$"}, {"flags": 0, "span_num": 140, "line_num": 0, "block_num": 0, "bbox": [597.93083, 325.81922, 629.29693, 337.43135], "text": "51,274"}, {"flags": 0, "span_num": 141, "line_num": 0, "block_num": 0, "bbox": [662.69398, 325.81922, 668.47468, 337.43135], "text": "$"}, {"flags": 0, "span_num": 142, "line_num": 0, "block_num": 0, "bbox": [671.4889, 325.81922, 702.85504, 337.43135], "text": "48,415"}, {"flags": 0, "span_num": 143, "line_num": 0, "block_num": 0, "bbox": [29.454549999999998, 341.8092, 89.95681, 353.42133], "text": "LIABILITIES"}, {"flags": 0, "span_num": 144, "line_num": 0, "block_num": 0, "bbox": [93.41812, 341.8092, 115.31620000000001, 353.42133], "text": "AND"}, {"flags": 0, "span_num": 145, "line_num": 0, "block_num": 0, "bbox": [118.20401000000001, 341.8092, 207.44264, 353.42133], "text": "STOCKHOLDERS\u2019"}, {"flags": 0, "span_num": 146, "line_num": 0, "block_num": 0, "bbox": [210.95119, 341.8092, 249.86575, 353.42133], "text": "EQUITY"}, {"flags": 0, "span_num": 147, "line_num": 0, "block_num": 0, "bbox": [29.454549999999998, 353.80415, 66.49673, 365.41628], "text": "Current"}, {"flags": 0, "span_num": 148, "line_num": 0, "block_num": 0, "bbox": [69.43178, 353.80415, 115.18970999999999, 365.41628], "text": "liabilities"}, {"flags": 0, "span_num": 149, "line_num": 0, "block_num": 0, "bbox": [42.24726, 365.7991, 75.51778, 377.41123], "text": "Current"}, {"flags": 0, "span_num": 150, "line_num": 0, "block_num": 0, "bbox": [79.02631, 365.7991, 124.20060000000001, 377.41123], "text": "maturities"}, {"flags": 0, "span_num": 151, "line_num": 0, "block_num": 0, "bbox": [127.79854, 365.7991, 136.28317, 377.41123], "text": "of"}, {"flags": 0, "span_num": 152, "line_num": 0, "block_num": 0, "bbox": [139.79172, 365.7991, 182.83048, 377.41123], "text": "long-term"}, {"flags": 0, "span_num": 153, "line_num": 0, "block_num": 0, "bbox": [186.16531, 365.7991, 205.84355, 377.41123], "text": "debt"}, {"flags": 0, "span_num": 154, "line_num": 0, "block_num": 0, "bbox": [209.3521, 365.7991, 226.32641, 377.41123], "text": "and"}, {"flags": 0, "span_num": 155, "line_num": 0, "block_num": 0, "bbox": [229.34071, 365.7991, 259.63401, 377.41123], "text": "capital"}, {"flags": 0, "span_num": 156, "line_num": 0, "block_num": 0, "bbox": [262.92159, 365.7991, 292.90451, 377.41123], "text": "leases"}, {"flags": 0, "span_num": 157, "line_num": 0, "block_num": 0, "bbox": [589.13583, 365.7991, 594.91652, 377.41123], "text": "$"}, {"flags": 0, "span_num": 158, "line_num": 0, "block_num": 0, "bbox": [603.52764, 365.7991, 629.29693, 377.41123], "text": "1,855"}, {"flags": 0, "span_num": 159, "line_num": 0, "block_num": 0, "bbox": [662.69398, 365.7991, 668.47468, 377.41123], "text": "$"}, {"flags": 0, "span_num": 160, "line_num": 0, "block_num": 0, "bbox": [677.08572, 365.7991, 702.85504, 377.41123], "text": "2,231"}, {"flags": 0, "span_num": 161, "line_num": 0, "block_num": 0, "bbox": [42.24726, 377.78912, 85.82245, 389.40125], "text": "Accounts"}, {"flags": 0, "span_num": 162, "line_num": 0, "block_num": 0, "bbox": [89.42039, 377.78912, 125.58379, 389.40125], "text": "payable"}, {"flags": 0, "span_num": 163, "line_num": 0, "block_num": 0, "bbox": [603.52764, 377.78912, 629.29693, 389.40125], "text": "1,592"}, {"flags": 0, "span_num": 164, "line_num": 0, "block_num": 0, "bbox": [677.08572, 377.78912, 702.85504, 389.40125], "text": "1,563"}, {"flags": 0, "span_num": 165, "line_num": 0, "block_num": 0, "bbox": [42.24726, 389.78407, 80.80929, 401.3962], "text": "Accrued"}, {"flags": 0, "span_num": 166, "line_num": 0, "block_num": 0, "bbox": [83.82359, 389.78407, 119.40332000000001, 401.3962], "text": "salaries"}, {"flags": 0, "span_num": 167, "line_num": 0, "block_num": 0, "bbox": [123.00128000000001, 389.78407, 139.97559, 401.3962], "text": "and"}, {"flags": 0, "span_num": 168, "line_num": 0, "block_num": 0, "bbox": [142.98989, 389.78407, 172.17327, 401.3962], "text": "wages"}, {"flags": 0, "span_num": 169, "line_num": 0, "block_num": 0, "bbox": [603.52764, 389.78407, 629.29693, 401.3962], "text": "1,516"}, {"flags": 0, "span_num": 170, "line_num": 0, "block_num": 0, "bbox": [677.08572, 389.78407, 702.85504, 401.3962], "text": "1,205"}, {"flags": 0, "span_num": 171, "line_num": 0, "block_num": 0, "bbox": [42.24726, 401.77408, 55.303110000000004, 413.38621], "text": "Air"}, {"flags": 0, "span_num": 172, "line_num": 0, "block_num": 0, "bbox": [58.238150000000005, 401.77408, 84.22336, 413.38621], "text": "traffic"}, {"flags": 0, "span_num": 173, "line_num": 0, "block_num": 0, "bbox": [87.8213, 401.77408, 119.40332000000001, 413.38621], "text": "liability"}, {"flags": 0, "span_num": 174, "line_num": 0, "block_num": 0, "bbox": [603.52764, 401.77408, 629.29693, 413.38621], "text": "3,912"}, {"flags": 0, "span_num": 175, "line_num": 0, "block_num": 0, "bbox": [677.08572, 401.77408, 702.85504, 413.38621], "text": "3,747"}, {"flags": 0, "span_num": 176, "line_num": 0, "block_num": 0, "bbox": [42.24726, 413.76903000000004, 75.42837, 425.38116], "text": "Loyalty"}, {"flags": 0, "span_num": 177, "line_num": 0, "block_num": 0, "bbox": [79.02631, 413.76903000000004, 116.46828, 425.38116], "text": "program"}, {"flags": 0, "span_num": 178, "line_num": 0, "block_num": 0, "bbox": [119.8031, 413.76903000000004, 151.3851, 425.38116], "text": "liability"}, {"flags": 0, "span_num": 179, "line_num": 0, "block_num": 0, "bbox": [603.52764, 413.76903000000004, 629.29693, 425.38116], "text": "2,789"}, {"flags": 0, "span_num": 180, "line_num": 0, "block_num": 0, "bbox": [677.08572, 413.76903000000004, 702.85504, 425.38116], "text": "2,525"}, {"flags": 0, "span_num": 181, "line_num": 0, "block_num": 0, "bbox": [42.24726, 425.76397999999995, 68.09582, 437.37611000000004], "text": "Other"}, {"flags": 0, "span_num": 182, "line_num": 0, "block_num": 0, "bbox": [71.03087, 425.76397999999995, 107.99381, 437.37611000000004], "text": "accrued"}, {"flags": 0, "span_num": 183, "line_num": 0, "block_num": 0, "bbox": [111.0081, 425.76397999999995, 150.58556, 437.37611000000004], "text": "liabilities"}, {"flags": 0, "span_num": 184, "line_num": 0, "block_num": 0, "bbox": [603.52764, 425.76397999999995, 629.29693, 437.37611000000004], "text": "2,208"}, {"flags": 0, "span_num": 185, "line_num": 0, "block_num": 0, "bbox": [677.08572, 425.76397999999995, 702.85504, 437.37611000000004], "text": "2,334"}, {"flags": 0, "span_num": 186, "line_num": 0, "block_num": 0, "bbox": [55.03998, 440.15594999999996, 78.13737, 451.76808000000005], "text": "Total"}, {"flags": 0, "span_num": 187, "line_num": 0, "block_num": 0, "bbox": [81.42495, 440.15594999999996, 113.09638000000001, 451.76808000000005], "text": "current"}, {"flags": 0, "span_num": 188, "line_num": 0, "block_num": 0, "bbox": [116.60491999999999, 440.15594999999996, 156.18237, 451.76808000000005], "text": "liabilities"}, {"flags": 0, "span_num": 189, "line_num": 0, "block_num": 0, "bbox": [597.93083, 440.15594999999996, 629.29693, 451.76808000000005], "text": "13,872"}, {"flags": 0, "span_num": 190, "line_num": 0, "block_num": 0, "bbox": [671.4889, 440.15594999999996, 702.85504, 451.76808000000005], "text": "13,605"}, {"flags": 0, "span_num": 191, "line_num": 0, "block_num": 0, "bbox": [29.454549999999998, 452.14597000000003, 84.88626, 463.7581], "text": "Noncurrent"}, {"flags": 0, "span_num": 192, "line_num": 0, "block_num": 0, "bbox": [87.8213, 452.14597000000003, 133.57923, 463.7581], "text": "liabilities"}, {"flags": 0, "span_num": 193, "line_num": 0, "block_num": 0, "bbox": [42.24726, 464.14092000000005, 88.48421, 475.75305000000003], "text": "Long-term"}, {"flags": 0, "span_num": 194, "line_num": 0, "block_num": 0, "bbox": [91.81903, 464.14092000000005, 111.49729, 475.75305000000003], "text": "debt"}, {"flags": 0, "span_num": 195, "line_num": 0, "block_num": 0, "bbox": [115.00583, 464.14092000000005, 131.98014, 475.75305000000003], "text": "and"}, {"flags": 0, "span_num": 196, "line_num": 0, "block_num": 0, "bbox": [134.99445, 464.14092000000005, 165.28775, 475.75305000000003], "text": "capital"}, {"flags": 0, "span_num": 197, "line_num": 0, "block_num": 0, "bbox": [168.57532, 464.14092000000005, 201.84582, 475.75305000000003], "text": "leases,"}, {"flags": 0, "span_num": 198, "line_num": 0, "block_num": 0, "bbox": [205.35438, 464.14092000000005, 219.43581, 475.75305000000003], "text": "net"}, {"flags": 0, "span_num": 199, "line_num": 0, "block_num": 0, "bbox": [222.94435, 464.14092000000005, 231.42897, 475.75305000000003], "text": "of"}, {"flags": 0, "span_num": 200, "line_num": 0, "block_num": 0, "bbox": [234.93753, 464.14092000000005, 266.60894, 475.75305000000003], "text": "current"}, {"flags": 0, "span_num": 201, "line_num": 0, "block_num": 0, "bbox": [270.1175, 464.14092000000005, 315.29178, 475.75305000000003], "text": "maturities"}, {"flags": 0, "span_num": 202, "line_num": 0, "block_num": 0, "bbox": [597.93083, 464.14092000000005, 629.29693, 475.75305000000003], "text": "22,489"}, {"flags": 0, "span_num": 203, "line_num": 0, "block_num": 0, "bbox": [671.4889, 464.14092000000005, 702.85504, 475.75305000000003], "text": "18,330"}, {"flags": 0, "span_num": 204, "line_num": 0, "block_num": 0, "bbox": [42.24726, 476.13586999999995, 80.00975, 487.74800000000005], "text": "Pension"}, {"flags": 0, "span_num": 205, "line_num": 0, "block_num": 0, "bbox": [83.02404, 476.13586999999995, 99.99835, 487.74800000000005], "text": "and"}, {"flags": 0, "span_num": 206, "line_num": 0, "block_num": 0, "bbox": [103.01266, 476.13586999999995, 169.06449, 487.74800000000005], "text": "postretirement"}, {"flags": 0, "span_num": 207, "line_num": 0, "block_num": 0, "bbox": [172.57305, 476.13586999999995, 208.95233, 487.74800000000005], "text": "benefits"}, {"flags": 0, "span_num": 208, "line_num": 0, "block_num": 0, "bbox": [603.52764, 476.13586999999995, 629.29693, 487.74800000000005], "text": "7,842"}, {"flags": 0, "span_num": 209, "line_num": 0, "block_num": 0, "bbox": [677.08572, 476.13586999999995, 702.85504, 487.74800000000005], "text": "7,450"}, {"flags": 0, "span_num": 210, "line_num": 0, "block_num": 0, "bbox": [42.24726, 488.12588000000005, 81.60884, 499.73801000000003], "text": "Deferred"}, {"flags": 0, "span_num": 211, "line_num": 0, "block_num": 0, "bbox": [84.62313, 488.12588000000005, 109.00925, 499.73801000000003], "text": "gains"}, {"flags": 0, "span_num": 212, "line_num": 0, "block_num": 0, "bbox": [112.60719, 488.12588000000005, 129.58151, 499.73801000000003], "text": "and"}, {"flags": 0, "span_num": 213, "line_num": 0, "block_num": 0, "bbox": [132.59581, 488.12588000000005, 166.66585, 499.73801000000003], "text": "credits,"}, {"flags": 0, "span_num": 214, "line_num": 0, "block_num": 0, "bbox": [170.17441, 488.12588000000005, 184.25585, 499.73801000000003], "text": "net"}, {"flags": 0, "span_num": 215, "line_num": 0, "block_num": 0, "bbox": [612.3226, 488.12588000000005, 629.29693, 499.73801000000003], "text": "526"}, {"flags": 0, "span_num": 216, "line_num": 0, "block_num": 0, "bbox": [685.88072, 488.12588000000005, 702.85504, 499.73801000000003], "text": "667"}, {"flags": 0, "span_num": 217, "line_num": 0, "block_num": 0, "bbox": [42.24726, 500.12082999999996, 68.09582, 511.73296000000005], "text": "Other"}, {"flags": 0, "span_num": 218, "line_num": 0, "block_num": 0, "bbox": [71.03087, 500.12082999999996, 110.60834, 511.73296000000005], "text": "liabilities"}, {"flags": 0, "span_num": 219, "line_num": 0, "block_num": 0, "bbox": [603.52764, 500.12082999999996, 629.29693, 511.73296000000005], "text": "2,760"}, {"flags": 0, "span_num": 220, "line_num": 0, "block_num": 0, "bbox": [677.08572, 500.12082999999996, 702.85504, 511.73296000000005], "text": "2,728"}, {"flags": 0, "span_num": 221, "line_num": 0, "block_num": 0, "bbox": [55.03998, 514.5128, 78.13737, 526.12493], "text": "Total"}, {"flags": 0, "span_num": 222, "line_num": 0, "block_num": 0, "bbox": [81.42495, 514.5128, 129.88681, 526.12493], "text": "noncurrent"}, {"flags": 0, "span_num": 223, "line_num": 0, "block_num": 0, "bbox": [133.39536, 514.5128, 172.97282, 526.12493], "text": "liabilities"}, {"flags": 0, "span_num": 224, "line_num": 0, "block_num": 0, "bbox": [597.93083, 514.5128, 629.29693, 526.12493], "text": "33,617"}, {"flags": 0, "span_num": 225, "line_num": 0, "block_num": 0, "bbox": [671.4889, 514.5128, 702.85504, 526.12493], "text": "29,175"}, {"flags": 0, "span_num": 226, "line_num": 0, "block_num": 0, "bbox": [55.03998, 526.50282, 119.40332000000001, 538.11495], "text": "Commitments"}, {"flags": 0, "span_num": 227, "line_num": 0, "block_num": 0, "bbox": [123.00128000000001, 526.50282, 139.97559, 538.11495], "text": "and"}, {"flags": 0, "span_num": 228, "line_num": 0, "block_num": 0, "bbox": [142.98989, 526.50282, 206.5537, 538.11495], "text": "contingencies"}, {"flags": 0, "span_num": 229, "line_num": 0, "block_num": 0, "bbox": [210.15165, 526.50282, 235.12141, 538.11495], "text": "(Note"}, {"flags": 0, "span_num": 230, "line_num": 0, "block_num": 0, "bbox": [238.13571, 526.50282, 252.79066, 538.11495], "text": "11)"}, {"flags": 0, "span_num": 231, "line_num": 0, "block_num": 0, "bbox": [29.454549999999998, 538.49777, 97.90502, 550.1099], "text": "Stockholders\u2019"}, {"flags": 0, "span_num": 232, "line_num": 0, "block_num": 0, "bbox": [101.41357, 538.49777, 131.98014, 550.1099], "text": "equity"}, {"flags": 0, "span_num": 233, "line_num": 0, "block_num": 0, "bbox": [42.24726, 550.49268, 84.00746, 562.10485], "text": "Common"}, {"flags": 0, "span_num": 234, "line_num": 0, "block_num": 0, "bbox": [87.02176, 550.49268, 115.495, 562.10485], "text": "stock,"}, {"flags": 0, "span_num": 235, "line_num": 0, "block_num": 0, "bbox": [119.00354999999999, 550.49268, 144.77286, 562.10485], "text": "$0.01"}, {"flags": 0, "span_num": 236, "line_num": 0, "block_num": 0, "bbox": [147.78715, 550.49268, 162.4421, 562.10485], "text": "par"}, {"flags": 0, "span_num": 237, "line_num": 0, "block_num": 0, "bbox": [165.37714, 550.49268, 193.05084, 562.10485], "text": "value;"}, {"flags": 0, "span_num": 238, "line_num": 0, "block_num": 0, "bbox": [196.55938, 550.49268, 262.30592, 562.10485], "text": "1,750,000,000"}, {"flags": 0, "span_num": 239, "line_num": 0, "block_num": 0, "bbox": [265.32023, 550.49268, 296.10269, 562.10485], "text": "shares"}, {"flags": 0, "span_num": 240, "line_num": 0, "block_num": 0, "bbox": [299.70065, 550.49268, 350.56116, 562.10485], "text": "authorized,"}, {"flags": 0, "span_num": 241, "line_num": 0, "block_num": 0, "bbox": [354.06968, 550.49268, 411.02122, 562.10485], "text": "507,294,153"}, {"flags": 0, "span_num": 242, "line_num": 0, "block_num": 0, "bbox": [414.03552, 550.49268, 444.81801, 562.10485], "text": "shares"}, {"flags": 0, "span_num": 243, "line_num": 0, "block_num": 0, "bbox": [448.41596, 550.49268, 478.98252, 562.10485], "text": "issued"}, {"flags": 0, "span_num": 244, "line_num": 0, "block_num": 0, "bbox": [481.99682, 550.49268, 498.97114999999997, 562.10485], "text": "and"}, {"flags": 0, "span_num": 245, "line_num": 0, "block_num": 0, "bbox": [501.98545, 550.49268, 555.73881, 562.10485], "text": "outstanding"}, {"flags": 0, "span_num": 246, "line_num": 0, "block_num": 0, "bbox": [55.03998, 562.48269, 63.52459, 574.09486], "text": "at"}, {"flags": 0, "span_num": 247, "line_num": 0, "block_num": 0, "bbox": [67.03315, 562.48269, 114.46941000000001, 574.09486], "text": "December"}, {"flags": 0, "span_num": 248, "line_num": 0, "block_num": 0, "bbox": [117.40446, 562.48269, 131.4859, 574.09486], "text": "31,"}, {"flags": 0, "span_num": 249, "line_num": 0, "block_num": 0, "bbox": [134.99445, 562.48269, 160.26949, 574.09486], "text": "2016;"}, {"flags": 0, "span_num": 250, "line_num": 0, "block_num": 0, "bbox": [163.77805, 562.48269, 220.72961, 574.09486], "text": "624,622,381"}, {"flags": 0, "span_num": 251, "line_num": 0, "block_num": 0, "bbox": [223.7439, 562.48269, 254.52639, 574.09486], "text": "shares"}, {"flags": 0, "span_num": 252, "line_num": 0, "block_num": 0, "bbox": [258.12432, 562.48269, 288.69091, 574.09486], "text": "issued"}, {"flags": 0, "span_num": 253, "line_num": 0, "block_num": 0, "bbox": [291.7052, 562.48269, 308.67952, 574.09486], "text": "and"}, {"flags": 0, "span_num": 254, "line_num": 0, "block_num": 0, "bbox": [311.69382, 562.48269, 365.44719, 574.09486], "text": "outstanding"}, {"flags": 0, "span_num": 255, "line_num": 0, "block_num": 0, "bbox": [368.46149, 562.48269, 376.94611, 574.09486], "text": "at"}, {"flags": 0, "span_num": 256, "line_num": 0, "block_num": 0, "bbox": [380.45467, 562.48269, 427.89093, 574.09486], "text": "December"}, {"flags": 0, "span_num": 257, "line_num": 0, "block_num": 0, "bbox": [430.82597, 562.48269, 444.90741, 574.09486], "text": "31,"}, {"flags": 0, "span_num": 258, "line_num": 0, "block_num": 0, "bbox": [448.41596, 562.48269, 470.9871, 574.09486], "text": "2015"}, {"flags": 0, "span_num": 259, "line_num": 0, "block_num": 0, "bbox": [623.51623, 562.48269, 629.29693, 574.09486], "text": "5"}, {"flags": 0, "span_num": 260, "line_num": 0, "block_num": 0, "bbox": [697.07435, 562.48269, 702.85504, 574.09486], "text": "6"}, {"flags": 0, "span_num": 261, "line_num": 0, "block_num": 0, "bbox": [42.24726, 574.47764, 87.7319, 586.08981], "text": "Additional"}, {"flags": 0, "span_num": 262, "line_num": 0, "block_num": 0, "bbox": [91.01948, 574.47764, 121.58606, 586.08981], "text": "paid-in"}, {"flags": 0, "span_num": 263, "line_num": 0, "block_num": 0, "bbox": [124.60036, 574.47764, 154.89366, 586.08981], "text": "capital"}, {"flags": 0, "span_num": 264, "line_num": 0, "block_num": 0, "bbox": [603.52764, 574.47764, 629.29693, 586.08981], "text": "7,223"}, {"flags": 0, "span_num": 265, "line_num": 0, "block_num": 0, "bbox": [671.4889, 574.47764, 702.85504, 586.08981], "text": "11,591"}, {"flags": 0, "span_num": 266, "line_num": 0, "block_num": 0, "bbox": [42.24726, 586.47259, 103.19654, 598.08476], "text": "Accumulated"}, {"flags": 0, "span_num": 267, "line_num": 0, "block_num": 0, "bbox": [106.21084, 586.47259, 129.66076, 598.08476], "text": "other"}, {"flags": 0, "span_num": 268, "line_num": 0, "block_num": 0, "bbox": [132.59581, 586.47259, 203.13962, 598.08476], "text": "comprehensive"}, {"flags": 0, "span_num": 269, "line_num": 0, "block_num": 0, "bbox": [206.15392, 586.47259, 224.94322, 598.08476], "text": "loss"}, {"flags": 0, "span_num": 270, "line_num": 0, "block_num": 0, "bbox": [600.32946, 586.47259, 632.57437, 598.08476], "text": "(5,083)"}, {"flags": 0, "span_num": 271, "line_num": 0, "block_num": 0, "bbox": [673.88762, 586.47259, 706.13244, 598.08476], "text": "(4,732)"}, {"flags": 0, "span_num": 272, "line_num": 0, "block_num": 0, "bbox": [42.24726, 598.46261, 83.20792, 610.07478], "text": "Retained"}, {"flags": 0, "span_num": 273, "line_num": 0, "block_num": 0, "bbox": [86.22221, 598.46261, 125.00013999999999, 610.07478], "text": "earnings"}, {"flags": 0, "span_num": 274, "line_num": 0, "block_num": 0, "bbox": [128.59808, 598.46261, 163.24164, 610.07478], "text": "(deficit)"}, {"flags": 0, "span_num": 275, "line_num": 0, "block_num": 0, "bbox": [603.52764, 598.46261, 629.29693, 610.07478], "text": "1,640"}, {"flags": 0, "span_num": 276, "line_num": 0, "block_num": 0, "bbox": [673.88762, 598.46261, 706.13244, 610.07478], "text": "(1,230)"}, {"flags": 0, "span_num": 277, "line_num": 0, "block_num": 0, "bbox": [55.03998, 612.85458, 78.13737, 624.46675], "text": "Total"}, {"flags": 0, "span_num": 278, "line_num": 0, "block_num": 0, "bbox": [81.42495, 612.85458, 142.90048, 624.46675], "text": "stockholders\u2019"}, {"flags": 0, "span_num": 279, "line_num": 0, "block_num": 0, "bbox": [146.18806, 612.85458, 173.77237, 624.46675], "text": "equity"}, {"flags": 0, "span_num": 280, "line_num": 0, "block_num": 0, "bbox": [603.52764, 612.85458, 629.29693, 624.46675], "text": "3,785"}, {"flags": 0, "span_num": 281, "line_num": 0, "block_num": 0, "bbox": [677.08572, 612.85458, 702.85504, 624.46675], "text": "5,635"}, {"flags": 0, "span_num": 282, "line_num": 0, "block_num": 0, "bbox": [67.83269, 627.24654, 92.3082, 638.85871], "text": "Total"}, {"flags": 0, "span_num": 283, "line_num": 0, "block_num": 0, "bbox": [95.81675, 627.24654, 141.57468, 638.85871], "text": "liabilities"}, {"flags": 0, "span_num": 284, "line_num": 0, "block_num": 0, "bbox": [144.58898, 627.24654, 162.93127, 638.85871], "text": "and"}, {"flags": 0, "span_num": 285, "line_num": 0, "block_num": 0, "bbox": [166.17669, 627.24654, 233.02806, 638.85871], "text": "stockholders\u2019"}, {"flags": 0, "span_num": 286, "line_num": 0, "block_num": 0, "bbox": [236.53662, 627.24654, 267.10319, 638.85871], "text": "equity"}, {"flags": 0, "span_num": 287, "line_num": 0, "block_num": 0, "bbox": [589.13583, 627.24654, 594.91652, 638.85871], "text": "$"}, {"flags": 0, "span_num": 288, "line_num": 0, "block_num": 0, "bbox": [597.93083, 627.24654, 629.29693, 638.85871], "text": "51,274"}, {"flags": 0, "span_num": 289, "line_num": 0, "block_num": 0, "bbox": [662.69398, 627.24654, 668.47468, 638.85871], "text": "$"}, {"flags": 0, "span_num": 290, "line_num": 0, "block_num": 0, "bbox": [671.4889, 627.24654, 702.85504, 638.85871], "text": "48,415"}, {"flags": 0, "span_num": 291, "line_num": 0, "block_num": 0, "bbox": [223.7439, 652.83445, 242.31731000000002, 664.44662], "text": "See"}, {"flags": 0, "span_num": 292, "line_num": 0, "block_num": 0, "bbox": [245.33162, 652.83445, 312.67724, 664.44662], "text": "accompanying"}, {"flags": 0, "span_num": 293, "line_num": 0, "block_num": 0, "bbox": [315.69155, 652.83445, 340.87722, 664.44662], "text": "notes"}, {"flags": 0, "span_num": 294, "line_num": 0, "block_num": 0, "bbox": [344.47517, 652.83445, 353.45405, 664.44662], "text": "to"}, {"flags": 0, "span_num": 295, "line_num": 0, "block_num": 0, "bbox": [356.46831, 652.83445, 415.01894, 664.44662], "text": "consolidated"}, {"flags": 0, "span_num": 296, "line_num": 0, "block_num": 0, "bbox": [418.03325, 652.83445, 456.32202, 664.44662], "text": "financial"}, {"flags": 0, "span_num": 297, "line_num": 0, "block_num": 0, "bbox": [459.6096, 652.83445, 514.46779, 664.44662], "text": "statements."}]