[{"flags": 0, "span_num": 70, "line_num": 0, "block_num": 0, "bbox": [29.191920000000003, 0, 73.81314, 10.948180000000008], "text": "Analysis"}, {"flags": 0, "span_num": 71, "line_num": 0, "block_num": 0, "bbox": [78.01136, 0, 88.08712, 10.948180000000008], "text": "of"}, {"flags": 0, "span_num": 72, "line_num": 0, "block_num": 0, "bbox": [92.28535, 0, 140.50503, 10.948180000000008], "text": "Financial"}, {"flags": 0, "span_num": 73, "line_num": 0, "block_num": 0, "bbox": [144.70325, 0, 195.80177, 10.948180000000008], "text": "Condition"}, {"flags": 0, "span_num": 74, "line_num": 0, "block_num": 0, "bbox": [200.00002, 0, 219.43185, 10.948180000000008], "text": "and"}, {"flags": 0, "span_num": 75, "line_num": 0, "block_num": 0, "bbox": [223.6301, 0, 264.17305, 10.948180000000008], "text": "Results"}, {"flags": 0, "span_num": 76, "line_num": 0, "block_num": 0, "bbox": [268.3713, 0, 278.44707, 10.948180000000008], "text": "of"}, {"flags": 0, "span_num": 77, "line_num": 0, "block_num": 0, "bbox": [282.64532, 0, 340.70087, 10.948180000000008], "text": "Operations"}, {"flags": 0, "span_num": 78, "line_num": 0, "block_num": 0, "bbox": [344.89912, 0, 364.33095, 10.948180000000008], "text": "and"}, {"flags": 0, "span_num": 79, "line_num": 0, "block_num": 0, "bbox": [368.5292, 0, 399.95595, 10.948180000000008], "text": "Notes"}, {"flags": 0, "span_num": 80, "line_num": 0, "block_num": 0, "bbox": [404.1542, 0, 411.35118, 10.948180000000008], "text": "1"}, {"flags": 0, "span_num": 81, "line_num": 0, "block_num": 0, "bbox": [415.54943, 0, 434.98127, 10.948180000000008], "text": "and"}, {"flags": 0, "span_num": 82, "line_num": 0, "block_num": 0, "bbox": [439.17951, 0, 446.3765, 10.948180000000008], "text": "2"}, {"flags": 0, "span_num": 83, "line_num": 0, "block_num": 0, "bbox": [450.57475, 0, 461.61009, 10.948180000000008], "text": "to"}, {"flags": 0, "span_num": 84, "line_num": 0, "block_num": 0, "bbox": [465.80834, 0, 535.85885, 10.948180000000008], "text": "Consolidated"}, {"flags": 0, "span_num": 85, "line_num": 0, "block_num": 0, "bbox": [540.0571, 0, 588.27684, 10.948180000000008], "text": "Financial"}, {"flags": 0, "span_num": 86, "line_num": 0, "block_num": 0, "bbox": [592.47509, 0, 658.68717, 10.948180000000008], "text": "Statements."}, {"flags": 0, "span_num": 87, "line_num": 0, "block_num": 0, "bbox": [29.191920000000003, 20.635009999999994, 52.10858, 31.297889999999995], "text": "Years"}, {"flags": 0, "span_num": 88, "line_num": 0, "block_num": 0, "bbox": [55.422979999999995, 20.635009999999994, 81.36996, 31.297889999999995], "text": "Ended"}, {"flags": 0, "span_num": 89, "line_num": 0, "block_num": 0, "bbox": [84.68436, 20.635009999999994, 127.48741000000001, 31.297889999999995], "text": "December"}, {"flags": 0, "span_num": 90, "line_num": 0, "block_num": 0, "bbox": [130.8018, 20.635009999999994, 145.00635, 31.297889999999995], "text": "31,"}, {"flags": 0, "span_num": 91, "line_num": 0, "block_num": 0, "bbox": [29.191920000000003, 31.44815, 38.05556, 40.52516], "text": "(in"}, {"flags": 0, "span_num": 92, "line_num": 0, "block_num": 0, "bbox": [40.92804, 31.44815, 71.13007, 40.52516], "text": "millions)"}, {"flags": 0, "span_num": 93, "line_num": 0, "block_num": 0, "bbox": [327.67676, 30.10470000000001, 350.40403, 40.76759000000001], "text": "2007"}, {"flags": 0, "span_num": 94, "line_num": 0, "block_num": 0, "bbox": [401.46464, 29.243269999999995, 431.09979, 40.76759000000001], "text": "2006(a)"}, {"flags": 0, "span_num": 95, "line_num": 0, "block_num": 0, "bbox": [482.14645, 29.243269999999995, 511.7816, 40.76759000000001], "text": "2005(a)"}, {"flags": 0, "span_num": 96, "line_num": 0, "block_num": 0, "bbox": [562.8283, 29.243269999999995, 592.46345, 40.76759000000001], "text": "2004(a)"}, {"flags": 0, "span_num": 97, "line_num": 0, "block_num": 0, "bbox": [643.51007, 29.243269999999995, 673.14518, 40.76759000000001], "text": "2003(a)"}, {"flags": 0, "span_num": 98, "line_num": 0, "block_num": 0, "bbox": [29.191920000000003, 48.71077, 65.46718, 60.580720000000014], "text": "General"}, {"flags": 0, "span_num": 99, "line_num": 0, "block_num": 0, "bbox": [69.2235, 48.71077, 115.15781999999999, 60.580720000000014], "text": "Insurance"}, {"flags": 0, "span_num": 100, "line_num": 0, "block_num": 0, "bbox": [118.91414, 48.71077, 171.93178, 60.580720000000014], "text": "operations:"}, {"flags": 0, "span_num": 101, "line_num": 0, "block_num": 0, "bbox": [39.29318, 62.59951000000001, 66.98257, 74.46946], "text": "Gross"}, {"flags": 0, "span_num": 102, "line_num": 0, "block_num": 0, "bbox": [70.73889, 62.59951000000001, 117.4256, 74.46946], "text": "premiums"}, {"flags": 0, "span_num": 103, "line_num": 0, "block_num": 0, "bbox": [121.18191999999999, 62.59951000000001, 152.73496, 74.46946], "text": "written"}, {"flags": 0, "span_num": 104, "line_num": 0, "block_num": 0, "bbox": [292.44936, 62.38486, 298.88876, 74.46946], "text": "$"}, {"flags": 0, "span_num": 105, "line_num": 0, "block_num": 0, "bbox": [315.00014, 62.38486, 350.41683, 74.46946], "text": "58,798"}, {"flags": 0, "span_num": 106, "line_num": 0, "block_num": 0, "bbox": [373.13069, 62.59951000000001, 379.57009, 74.46946], "text": "$"}, {"flags": 0, "span_num": 107, "line_num": 0, "block_num": 0, "bbox": [395.68145, 62.59951000000001, 431.09813, 74.46946], "text": "56,280"}, {"flags": 0, "span_num": 108, "line_num": 0, "block_num": 0, "bbox": [453.81312, 62.59951000000001, 460.25252, 74.46946], "text": "$"}, {"flags": 0, "span_num": 109, "line_num": 0, "block_num": 0, "bbox": [476.36387, 62.59951000000001, 511.78056000000004, 74.46946], "text": "52,725"}, {"flags": 0, "span_num": 110, "line_num": 0, "block_num": 0, "bbox": [534.49658, 62.59951000000001, 540.93598, 74.46946], "text": "$"}, {"flags": 0, "span_num": 111, "line_num": 0, "block_num": 0, "bbox": [557.04734, 62.59951000000001, 592.46403, 74.46946], "text": "52,046"}, {"flags": 0, "span_num": 112, "line_num": 0, "block_num": 0, "bbox": [615.18005, 62.59951000000001, 621.61945, 74.46946], "text": "$"}, {"flags": 0, "span_num": 113, "line_num": 0, "block_num": 0, "bbox": [637.73085, 62.59951000000001, 673.14734, 74.46946], "text": "46,938"}, {"flags": 0, "span_num": 114, "line_num": 0, "block_num": 0, "bbox": [39.29212, 76.48823999999999, 55.60525, 88.35818999999998], "text": "Net"}, {"flags": 0, "span_num": 115, "line_num": 0, "block_num": 0, "bbox": [59.36157, 76.48823999999999, 106.04826, 88.35818999999998], "text": "premiums"}, {"flags": 0, "span_num": 116, "line_num": 0, "block_num": 0, "bbox": [109.80458, 76.48823999999999, 141.35762, 88.35818999999998], "text": "written"}, {"flags": 0, "span_num": 117, "line_num": 0, "block_num": 0, "bbox": [314.99906, 76.27359999999999, 350.41575, 88.35818999999998], "text": "47,067"}, {"flags": 0, "span_num": 118, "line_num": 0, "block_num": 0, "bbox": [395.68145, 76.48823999999999, 431.09813, 88.35818999999998], "text": "44,866"}, {"flags": 0, "span_num": 119, "line_num": 0, "block_num": 0, "bbox": [476.36387, 76.48823999999999, 511.78056000000004, 88.35818999999998], "text": "41,872"}, {"flags": 0, "span_num": 120, "line_num": 0, "block_num": 0, "bbox": [557.0463, 76.48823999999999, 592.46299, 88.35818999999998], "text": "40,623"}, {"flags": 0, "span_num": 121, "line_num": 0, "block_num": 0, "bbox": [637.72869, 76.48823999999999, 673.14518, 88.35818999999998], "text": "35,031"}, {"flags": 0, "span_num": 122, "line_num": 0, "block_num": 0, "bbox": [39.29212, 90.37698, 55.60525, 102.24693000000002], "text": "Net"}, {"flags": 0, "span_num": 123, "line_num": 0, "block_num": 0, "bbox": [59.36157, 90.37698, 106.04826, 102.24693000000002], "text": "premiums"}, {"flags": 0, "span_num": 124, "line_num": 0, "block_num": 0, "bbox": [109.80458, 90.37698, 142.4319, 102.24693000000002], "text": "earned"}, {"flags": 0, "span_num": 125, "line_num": 0, "block_num": 0, "bbox": [314.99906, 90.16233, 350.41575, 102.24693000000002], "text": "45,682"}, {"flags": 0, "span_num": 126, "line_num": 0, "block_num": 0, "bbox": [395.68145, 90.37698, 431.09813, 102.24693000000002], "text": "43,451"}, {"flags": 0, "span_num": 127, "line_num": 0, "block_num": 0, "bbox": [476.36387, 90.37698, 511.78056000000004, 102.24693000000002], "text": "40,809"}, {"flags": 0, "span_num": 128, "line_num": 0, "block_num": 0, "bbox": [557.0463, 90.37698, 592.46299, 102.24693000000002], "text": "38,537"}, {"flags": 0, "span_num": 129, "line_num": 0, "block_num": 0, "bbox": [637.72869, 90.37698, 673.14518, 102.24693000000002], "text": "31,306"}, {"flags": 0, "span_num": 130, "line_num": 0, "block_num": 0, "bbox": [39.29212, 104.26571000000001, 55.60525, 116.13565999999997], "text": "Net"}, {"flags": 0, "span_num": 131, "line_num": 0, "block_num": 0, "bbox": [59.36157, 104.26571000000001, 111.09135, 116.13565999999997], "text": "investment"}, {"flags": 0, "span_num": 132, "line_num": 0, "block_num": 0, "bbox": [114.84767, 102.93041, 156.67928, 116.13565999999997], "text": "income(b)"}, {"flags": 0, "span_num": 133, "line_num": 0, "block_num": 0, "bbox": [321.43938, 104.05167999999998, 350.41667, 116.13628], "text": "6,132"}, {"flags": 0, "span_num": 134, "line_num": 0, "block_num": 0, "bbox": [402.12069, 104.26632999999998, 431.09798, 116.13628], "text": "5,696"}, {"flags": 0, "span_num": 135, "line_num": 0, "block_num": 0, "bbox": [482.80312, 104.26632999999998, 511.78040999999996, 116.13628], "text": "4,031"}, {"flags": 0, "span_num": 136, "line_num": 0, "block_num": 0, "bbox": [563.48551, 104.26632999999998, 592.4628, 116.13628], "text": "3,196"}, {"flags": 0, "span_num": 137, "line_num": 0, "block_num": 0, "bbox": [644.1679, 104.26632999999998, 673.14503, 116.13628], "text": "2,566"}, {"flags": 0, "span_num": 138, "line_num": 0, "block_num": 0, "bbox": [39.29197, 118.15505999999999, 55.60509999999999, 130.02501], "text": "Net"}, {"flags": 0, "span_num": 139, "line_num": 0, "block_num": 0, "bbox": [59.36141000000001, 118.15505999999999, 95.63666, 130.02501], "text": "realized"}, {"flags": 0, "span_num": 140, "line_num": 0, "block_num": 0, "bbox": [99.39298, 118.15505999999999, 130.51672, 130.02501], "text": "capital"}, {"flags": 0, "span_num": 141, "line_num": 0, "block_num": 0, "bbox": [134.27304, 118.15505999999999, 159.38667, 130.02501], "text": "gains"}, {"flags": 0, "span_num": 142, "line_num": 0, "block_num": 0, "bbox": [163.14299, 118.15505999999999, 200.49146, 130.02501], "text": "(losses)"}, {"flags": 0, "span_num": 143, "line_num": 0, "block_num": 0, "bbox": [327.01913, 117.94042000000002, 354.48098, 130.02501], "text": "(106)"}, {"flags": 0, "span_num": 144, "line_num": 0, "block_num": 0, "bbox": [418.20631, 118.15505999999999, 431.08403, 130.02501], "text": "59"}, {"flags": 0, "span_num": 145, "line_num": 0, "block_num": 0, "bbox": [492.44822, 118.15505999999999, 511.76426000000004, 130.02501], "text": "334"}, {"flags": 0, "span_num": 146, "line_num": 0, "block_num": 0, "bbox": [573.12845, 118.15505999999999, 592.44449, 130.02501], "text": "228"}, {"flags": 0, "span_num": 147, "line_num": 0, "block_num": 0, "bbox": [657.04131, 118.15505999999999, 676.35616, 130.02501], "text": "(39)"}, {"flags": 0, "span_num": 148, "line_num": 0, "block_num": 0, "bbox": [39.29197, 132.04379999999998, 84.36774, 143.91375], "text": "Operating"}, {"flags": 0, "span_num": 149, "line_num": 0, "block_num": 0, "bbox": [88.12406, 130.70819, 145.37249, 143.91375], "text": "income(b)(c)(d)"}, {"flags": 0, "span_num": 150, "line_num": 0, "block_num": 0, "bbox": [314.99998, 131.82945999999998, 350.41667, 143.91406], "text": "10,526"}, {"flags": 0, "span_num": 151, "line_num": 0, "block_num": 0, "bbox": [395.68237, 132.04411, 431.09906, 143.91406], "text": "10,412"}, {"flags": 0, "span_num": 152, "line_num": 0, "block_num": 0, "bbox": [482.8042, 132.04411, 511.78148999999996, 143.91406], "text": "2,315"}, {"flags": 0, "span_num": 153, "line_num": 0, "block_num": 0, "bbox": [563.48659, 132.04411, 592.46388, 143.91406], "text": "3,177"}, {"flags": 0, "span_num": 154, "line_num": 0, "block_num": 0, "bbox": [644.16898, 132.04411, 673.14611, 143.91406], "text": "4,502"}, {"flags": 0, "span_num": 155, "line_num": 0, "block_num": 0, "bbox": [39.29304, 145.93284, 79.00264, 157.80277], "text": "Year-end"}, {"flags": 0, "span_num": 156, "line_num": 0, "block_num": 0, "bbox": [82.75896, 145.93284, 134.05947, 157.80277], "text": "identi\ufb01able"}, {"flags": 0, "span_num": 157, "line_num": 0, "block_num": 0, "bbox": [137.81579, 145.93284, 169.58345, 157.80277], "text": "assets"}, {"flags": 0, "span_num": 158, "line_num": 0, "block_num": 0, "bbox": [308.56058, 145.71820000000002, 350.41667, 157.80277], "text": "181,708"}, {"flags": 0, "span_num": 159, "line_num": 0, "block_num": 0, "bbox": [389.24189, 145.93284, 431.09798, 157.80277], "text": "167,004"}, {"flags": 0, "span_num": 160, "line_num": 0, "block_num": 0, "bbox": [469.92432, 145.93284, 511.78040999999996, 157.80277], "text": "150,667"}, {"flags": 0, "span_num": 161, "line_num": 0, "block_num": 0, "bbox": [550.60674, 145.93284, 592.46283, 157.80277], "text": "131,658"}, {"flags": 0, "span_num": 162, "line_num": 0, "block_num": 0, "bbox": [631.28917, 145.93284, 673.14503, 157.80277], "text": "117,511"}, {"flags": 0, "span_num": 163, "line_num": 0, "block_num": 0, "bbox": [29.191769999999998, 159.82155999999998, 72.4441, 171.69151], "text": "Statutory"}, {"flags": 0, "span_num": 164, "line_num": 0, "block_num": 0, "bbox": [76.20042, 158.48586999999998, 134.02147, 171.69182], "text": "measures(e):"}, {"flags": 0, "span_num": 165, "line_num": 0, "block_num": 0, "bbox": [39.29261, 173.71056, 82.54496, 185.58051], "text": "Statutory"}, {"flags": 0, "span_num": 166, "line_num": 0, "block_num": 0, "bbox": [86.30128, 173.71056, 144.14957, 185.58051], "text": "underwriting"}, {"flags": 0, "span_num": 167, "line_num": 0, "block_num": 0, "bbox": [147.9059, 173.71056, 171.94737, 185.58051], "text": "pro\ufb01t"}, {"flags": 0, "span_num": 168, "line_num": 0, "block_num": 0, "bbox": [175.70369, 172.37472000000002, 217.08961, 185.58051], "text": "(loss)(c)(d)"}, {"flags": 0, "span_num": 169, "line_num": 0, "block_num": 0, "bbox": [321.43938, 173.49608999999998, 350.41667, 185.58067], "text": "4,073"}, {"flags": 0, "span_num": 170, "line_num": 0, "block_num": 0, "bbox": [402.12069, 173.71071, 431.0937, 185.58067], "text": "4,408"}, {"flags": 0, "span_num": 171, "line_num": 0, "block_num": 0, "bbox": [479.56625, 173.71071, 514.97651, 185.58067], "text": "(2,165)"}, {"flags": 0, "span_num": 172, "line_num": 0, "block_num": 0, "bbox": [569.91316, 173.71071, 595.66645, 185.58067], "text": "(564)"}, {"flags": 0, "span_num": 173, "line_num": 0, "block_num": 0, "bbox": [644.16374, 173.71071, 673.13655, 185.58067], "text": "1,559"}, {"flags": 0, "span_num": 174, "line_num": 0, "block_num": 0, "bbox": [39.29197, 187.59940999999998, 61.6152, 199.46936], "text": "Loss"}, {"flags": 0, "span_num": 175, "line_num": 0, "block_num": 0, "bbox": [65.37151, 187.59940999999998, 86.40687, 199.46936], "text": "ratio"}, {"flags": 0, "span_num": 176, "line_num": 0, "block_num": 0, "bbox": [327.87771, 187.38479, 350.41559, 199.46936], "text": "65.6"}, {"flags": 0, "span_num": 177, "line_num": 0, "block_num": 0, "bbox": [408.55902, 187.59940999999998, 431.0969, 199.46936], "text": "64.6"}, {"flags": 0, "span_num": 178, "line_num": 0, "block_num": 0, "bbox": [489.2414, 187.59940999999998, 511.77928999999995, 199.46936], "text": "81.1"}, {"flags": 0, "span_num": 179, "line_num": 0, "block_num": 0, "bbox": [569.92379, 187.59940999999998, 592.46168, 199.46936], "text": "78.8"}, {"flags": 0, "span_num": 180, "line_num": 0, "block_num": 0, "bbox": [650.60618, 187.59940999999998, 673.14395, 199.46936], "text": "73.1"}, {"flags": 0, "span_num": 181, "line_num": 0, "block_num": 0, "bbox": [39.29089, 201.48811, 78.78584, 213.35806000000002], "text": "Expense"}, {"flags": 0, "span_num": 182, "line_num": 0, "block_num": 0, "bbox": [82.54216, 201.48811, 103.57751, 213.35806000000002], "text": "ratio"}, {"flags": 0, "span_num": 183, "line_num": 0, "block_num": 0, "bbox": [327.87663, 201.27348, 350.41451, 213.35806000000002], "text": "24.7"}, {"flags": 0, "span_num": 184, "line_num": 0, "block_num": 0, "bbox": [408.55794, 201.48811, 431.09582, 213.35806000000002], "text": "24.5"}, {"flags": 0, "span_num": 185, "line_num": 0, "block_num": 0, "bbox": [489.24033, 201.48811, 511.77820999999994, 213.35806000000002], "text": "23.6"}, {"flags": 0, "span_num": 186, "line_num": 0, "block_num": 0, "bbox": [569.92271, 201.48811, 592.4606, 213.35806000000002], "text": "21.5"}, {"flags": 0, "span_num": 187, "line_num": 0, "block_num": 0, "bbox": [650.6051, 201.48811, 673.14287, 213.35806000000002], "text": "19.6"}, {"flags": 0, "span_num": 188, "line_num": 0, "block_num": 0, "bbox": [39.28981, 219.79638, 86.29738, 231.66633000000002], "text": "Combined"}, {"flags": 0, "span_num": 189, "line_num": 0, "block_num": 0, "bbox": [90.0537, 218.46058, 119.00883999999999, 231.66633000000002], "text": "ratio(d)"}, {"flags": 0, "span_num": 190, "line_num": 0, "block_num": 0, "bbox": [327.87878, 219.58195, 350.41667, 231.66652], "text": "90.3"}, {"flags": 0, "span_num": 191, "line_num": 0, "block_num": 0, "bbox": [408.56009, 219.79656999999997, 431.09798, 231.66652], "text": "89.1"}, {"flags": 0, "span_num": 192, "line_num": 0, "block_num": 0, "bbox": [482.80312, 219.79656999999997, 511.78040999999996, 231.66652], "text": "104.7"}, {"flags": 0, "span_num": 193, "line_num": 0, "block_num": 0, "bbox": [563.48551, 219.79656999999997, 592.4628, 231.66652], "text": "100.3"}, {"flags": 0, "span_num": 194, "line_num": 0, "block_num": 0, "bbox": [650.60734, 219.79656999999997, 673.14511, 231.66652], "text": "92.7"}, {"flags": 0, "span_num": 195, "line_num": 0, "block_num": 0, "bbox": [29.191769999999998, 239.36696999999998, 46.14884, 251.23692], "text": "Life"}, {"flags": 0, "span_num": 196, "line_num": 0, "block_num": 0, "bbox": [49.905150000000006, 239.36696999999998, 95.83948, 251.23692], "text": "Insurance"}, {"flags": 0, "span_num": 197, "line_num": 0, "block_num": 0, "bbox": [99.5958, 239.36696999999998, 106.89378, 251.23692], "text": "&"}, {"flags": 0, "span_num": 198, "line_num": 0, "block_num": 0, "bbox": [110.6501, 239.36696999999998, 162.27472, 251.23692], "text": "Retirement"}, {"flags": 0, "span_num": 199, "line_num": 0, "block_num": 0, "bbox": [166.03104, 239.36696999999998, 206.70762, 251.23692], "text": "Services"}, {"flags": 0, "span_num": 200, "line_num": 0, "block_num": 0, "bbox": [210.46394, 239.36696999999998, 263.48159, 251.23692], "text": "operations:"}, {"flags": 0, "span_num": 201, "line_num": 0, "block_num": 0, "bbox": [39.29303, 253.25567, 86.19328, 265.12562], "text": "Premiums"}, {"flags": 0, "span_num": 202, "line_num": 0, "block_num": 0, "bbox": [89.9496, 253.25567, 107.33595, 265.12562], "text": "and"}, {"flags": 0, "span_num": 203, "line_num": 0, "block_num": 0, "bbox": [111.09227, 253.25567, 135.34731, 265.12562], "text": "other"}, {"flags": 0, "span_num": 204, "line_num": 0, "block_num": 0, "bbox": [139.10364, 253.25567, 208.0051, 265.12562], "text": "considerations"}, {"flags": 0, "span_num": 205, "line_num": 0, "block_num": 0, "bbox": [314.99998, 253.04104, 350.41667, 265.12562], "text": "33,627"}, {"flags": 0, "span_num": 206, "line_num": 0, "block_num": 0, "bbox": [395.68237, 253.25567, 431.09906, 265.12562], "text": "30,766"}, {"flags": 0, "span_num": 207, "line_num": 0, "block_num": 0, "bbox": [476.3648, 253.25567, 511.78148999999996, 265.12562], "text": "29,501"}, {"flags": 0, "span_num": 208, "line_num": 0, "block_num": 0, "bbox": [557.04722, 253.25567, 592.46391, 265.12562], "text": "28,167"}, {"flags": 0, "span_num": 209, "line_num": 0, "block_num": 0, "bbox": [637.72961, 253.25567, 673.14611, 265.12562], "text": "23,568"}, {"flags": 0, "span_num": 210, "line_num": 0, "block_num": 0, "bbox": [39.29304, 267.14436, 55.606179999999995, 279.01432], "text": "Net"}, {"flags": 0, "span_num": 211, "line_num": 0, "block_num": 0, "bbox": [59.362489999999994, 267.14436, 111.09227, 279.01432], "text": "investment"}, {"flags": 0, "span_num": 212, "line_num": 0, "block_num": 0, "bbox": [114.8486, 265.80907, 156.67928, 279.01432], "text": "income(b)"}, {"flags": 0, "span_num": 213, "line_num": 0, "block_num": 0, "bbox": [314.99998, 266.93043, 350.41667, 279.01501], "text": "22,341"}, {"flags": 0, "span_num": 214, "line_num": 0, "block_num": 0, "bbox": [395.68237, 267.14506, 431.09906, 279.01501], "text": "20,024"}, {"flags": 0, "span_num": 215, "line_num": 0, "block_num": 0, "bbox": [476.3648, 267.14506, 511.78148999999996, 279.01501], "text": "18,677"}, {"flags": 0, "span_num": 216, "line_num": 0, "block_num": 0, "bbox": [557.04722, 267.14506, 592.46391, 279.01501], "text": "15,654"}, {"flags": 0, "span_num": 217, "line_num": 0, "block_num": 0, "bbox": [637.72961, 267.14506, 673.14611, 279.01501], "text": "13,278"}, {"flags": 0, "span_num": 218, "line_num": 0, "block_num": 0, "bbox": [39.29304, 281.03375, 55.606179999999995, 292.90371], "text": "Net"}, {"flags": 0, "span_num": 219, "line_num": 0, "block_num": 0, "bbox": [59.362489999999994, 281.03375, 95.63774, 292.90371], "text": "realized"}, {"flags": 0, "span_num": 220, "line_num": 0, "block_num": 0, "bbox": [99.39406, 281.03375, 130.5178, 292.90371], "text": "capital"}, {"flags": 0, "span_num": 221, "line_num": 0, "block_num": 0, "bbox": [134.27412, 281.03375, 159.38775, 292.90371], "text": "gains"}, {"flags": 0, "span_num": 222, "line_num": 0, "block_num": 0, "bbox": [163.14407, 279.69796, 206.7424, 292.90371], "text": "(losses)(f)"}, {"flags": 0, "span_num": 223, "line_num": 0, "block_num": 0, "bbox": [317.34849, 280.81932, 354.48237, 292.9039], "text": "(2,398)"}, {"flags": 0, "span_num": 224, "line_num": 0, "block_num": 0, "bbox": [418.20658, 281.03395, 431.0843, 292.9039], "text": "88"}, {"flags": 0, "span_num": 225, "line_num": 0, "block_num": 0, "bbox": [489.24059, 281.03395, 514.99389, 292.9039], "text": "(158)"}, {"flags": 0, "span_num": 226, "line_num": 0, "block_num": 0, "bbox": [579.57675, 281.03395, 592.45555, 292.9039], "text": "45"}, {"flags": 0, "span_num": 227, "line_num": 0, "block_num": 0, "bbox": [653.81977, 281.03395, 673.13571, 292.9039], "text": "362"}, {"flags": 0, "span_num": 228, "line_num": 0, "block_num": 0, "bbox": [39.29224, 294.92264, 84.36801, 306.79259], "text": "Operating"}, {"flags": 0, "span_num": 229, "line_num": 0, "block_num": 0, "bbox": [88.12433, 293.58684, 136.20582, 306.79259], "text": "income(b)(f)"}, {"flags": 0, "span_num": 230, "line_num": 0, "block_num": 0, "bbox": [321.43938, 294.70821, 350.41667, 306.79279], "text": "8,186"}, {"flags": 0, "span_num": 231, "line_num": 0, "block_num": 0, "bbox": [395.68237, 294.92284, 431.09906, 306.79279], "text": "10,121"}, {"flags": 0, "span_num": 232, "line_num": 0, "block_num": 0, "bbox": [482.8042, 294.92284, 511.78148999999996, 306.79279], "text": "8,965"}, {"flags": 0, "span_num": 233, "line_num": 0, "block_num": 0, "bbox": [563.48659, 294.92284, 592.46388, 306.79279], "text": "7,968"}, {"flags": 0, "span_num": 234, "line_num": 0, "block_num": 0, "bbox": [644.16898, 294.92284, 673.14611, 306.79279], "text": "6,970"}, {"flags": 0, "span_num": 235, "line_num": 0, "block_num": 0, "bbox": [39.29304, 308.81153, 79.00264, 320.68148], "text": "Year-end"}, {"flags": 0, "span_num": 236, "line_num": 0, "block_num": 0, "bbox": [82.75896, 308.81153, 134.05947, 320.68148], "text": "identi\ufb01able"}, {"flags": 0, "span_num": 237, "line_num": 0, "block_num": 0, "bbox": [137.81579, 308.81153, 169.58345, 320.68148], "text": "assets"}, {"flags": 0, "span_num": 238, "line_num": 0, "block_num": 0, "bbox": [308.56058, 308.59691, 350.41667, 320.68148], "text": "615,386"}, {"flags": 0, "span_num": 239, "line_num": 0, "block_num": 0, "bbox": [389.24189, 308.81153, 431.09798, 320.68148], "text": "550,957"}, {"flags": 0, "span_num": 240, "line_num": 0, "block_num": 0, "bbox": [469.92432, 308.81153, 511.78040999999996, 320.68148], "text": "489,331"}, {"flags": 0, "span_num": 241, "line_num": 0, "block_num": 0, "bbox": [550.60674, 308.81153, 592.46283, 320.68148], "text": "457,071"}, {"flags": 0, "span_num": 242, "line_num": 0, "block_num": 0, "bbox": [631.28917, 308.81153, 673.14503, 320.68148], "text": "380,126"}, {"flags": 0, "span_num": 243, "line_num": 0, "block_num": 0, "bbox": [39.29193, 322.70023, 66.98132, 334.57018], "text": "Gross"}, {"flags": 0, "span_num": 244, "line_num": 0, "block_num": 0, "bbox": [70.73764, 322.70023, 116.45732000000001, 334.57018], "text": "insurance"}, {"flags": 0, "span_num": 245, "line_num": 0, "block_num": 0, "bbox": [120.21364, 322.70023, 128.58486, 334.57018], "text": "in"}, {"flags": 0, "span_num": 246, "line_num": 0, "block_num": 0, "bbox": [132.34225, 322.70023, 155.95337, 334.57018], "text": "force"}, {"flags": 0, "span_num": 247, "line_num": 0, "block_num": 0, "bbox": [159.70969, 322.70023, 168.93948, 334.57018], "text": "at"}, {"flags": 0, "span_num": 248, "line_num": 0, "block_num": 0, "bbox": [172.6958, 322.70023, 190.08215, 334.57018], "text": "end"}, {"flags": 0, "span_num": 249, "line_num": 0, "block_num": 0, "bbox": [193.83847, 322.70023, 202.85362, 334.57018], "text": "of"}, {"flags": 0, "span_num": 250, "line_num": 0, "block_num": 0, "bbox": [206.60994, 322.70023, 226.14277, 334.57018], "text": "year"}, {"flags": 0, "span_num": 251, "line_num": 0, "block_num": 0, "bbox": [298.88751, 322.4856, 350.40268, 334.57018], "text": "2,312,045"}, {"flags": 0, "span_num": 252, "line_num": 0, "block_num": 0, "bbox": [379.56882, 322.70023, 431.08399, 334.57018], "text": "2,070,600"}, {"flags": 0, "span_num": 253, "line_num": 0, "block_num": 0, "bbox": [460.25229, 322.70023, 511.76746, 334.57018], "text": "1,852,833"}, {"flags": 0, "span_num": 254, "line_num": 0, "block_num": 0, "bbox": [540.93575, 322.70023, 592.45093, 334.57018], "text": "1,858,094"}, {"flags": 0, "span_num": 255, "line_num": 0, "block_num": 0, "bbox": [621.61922, 322.70023, 673.13416, 334.57018], "text": "1,583,031"}, {"flags": 0, "span_num": 256, "line_num": 0, "block_num": 0, "bbox": [29.189610000000002, 342.27063, 70.40174, 354.14058], "text": "Financial"}, {"flags": 0, "span_num": 257, "line_num": 0, "block_num": 0, "bbox": [74.15806, 342.27063, 114.83463, 354.14058], "text": "Services"}, {"flags": 0, "span_num": 258, "line_num": 0, "block_num": 0, "bbox": [118.59094999999999, 342.27063, 171.60859, 354.14058], "text": "operations:"}, {"flags": 0, "span_num": 259, "line_num": 0, "block_num": 0, "bbox": [39.29087, 356.15932, 78.6785, 368.02927], "text": "Interest,"}, {"flags": 0, "span_num": 260, "line_num": 0, "block_num": 0, "bbox": [82.43482, 356.15932, 107.97775, 368.02927], "text": "lease"}, {"flags": 0, "span_num": 261, "line_num": 0, "block_num": 0, "bbox": [111.73407, 356.15932, 129.12042, 368.02927], "text": "and"}, {"flags": 0, "span_num": 262, "line_num": 0, "block_num": 0, "bbox": [132.87674, 356.15932, 166.57622, 368.02927], "text": "\ufb01nance"}, {"flags": 0, "span_num": 263, "line_num": 0, "block_num": 0, "bbox": [170.33254, 354.82421999999997, 223.23861, 368.02927], "text": "charges(g)(h)"}, {"flags": 0, "span_num": 264, "line_num": 0, "block_num": 0, "bbox": [317.34849, 355.94559000000004, 354.48237, 368.03016], "text": "(1,209)"}, {"flags": 0, "span_num": 265, "line_num": 0, "block_num": 0, "bbox": [402.12096, 356.16021, 431.09825, 368.03016], "text": "7,910"}, {"flags": 0, "span_num": 266, "line_num": 0, "block_num": 0, "bbox": [476.36399, 356.16021, 511.78067999999996, 368.03016], "text": "10,523"}, {"flags": 0, "span_num": 267, "line_num": 0, "block_num": 0, "bbox": [563.48582, 356.16021, 592.4631, 368.03016], "text": "7,495"}, {"flags": 0, "span_num": 268, "line_num": 0, "block_num": 0, "bbox": [644.1682, 356.16021, 673.14534, 368.03016], "text": "6,241"}, {"flags": 0, "span_num": 269, "line_num": 0, "block_num": 0, "bbox": [39.29224, 370.04891, 55.60536999999999, 381.91886], "text": "Net"}, {"flags": 0, "span_num": 270, "line_num": 0, "block_num": 0, "bbox": [59.36168000000001, 370.04891, 95.74426, 381.91886], "text": "realized"}, {"flags": 0, "span_num": 271, "line_num": 0, "block_num": 0, "bbox": [99.50059, 370.04891, 130.62432, 381.91886], "text": "capital"}, {"flags": 0, "span_num": 272, "line_num": 0, "block_num": 0, "bbox": [134.38065, 370.04891, 159.49427, 381.91886], "text": "gains"}, {"flags": 0, "span_num": 273, "line_num": 0, "block_num": 0, "bbox": [163.25059, 370.04891, 200.59906, 381.91886], "text": "(losses)"}, {"flags": 0, "span_num": 274, "line_num": 0, "block_num": 0, "bbox": [327.01936, 369.83428000000004, 354.48121, 381.91886], "text": "(100)"}, {"flags": 0, "span_num": 275, "line_num": 0, "block_num": 0, "bbox": [408.55925, 370.04891, 434.30822, 381.91886], "text": "(133)"}, {"flags": 0, "span_num": 276, "line_num": 0, "block_num": 0, "bbox": [492.45168, 370.04891, 511.76557, 381.91886], "text": "154"}, {"flags": 0, "span_num": 277, "line_num": 0, "block_num": 0, "bbox": [576.36235, 370.04891, 595.67408, 381.91886], "text": "(45)"}, {"flags": 0, "span_num": 278, "line_num": 0, "block_num": 0, "bbox": [653.81754, 370.04891, 673.13147, 381.91886], "text": "123"}, {"flags": 0, "span_num": 279, "line_num": 0, "block_num": 0, "bbox": [39.29112, 383.9376, 84.36689, 395.80755], "text": "Operating"}, {"flags": 0, "span_num": 280, "line_num": 0, "block_num": 0, "bbox": [88.12321, 383.9376, 122.03735, 395.80755], "text": "income"}, {"flags": 0, "span_num": 281, "line_num": 0, "block_num": 0, "bbox": [125.79368, 382.602, 167.32321, 395.80755], "text": "(loss)(g)(h)"}, {"flags": 0, "span_num": 282, "line_num": 0, "block_num": 0, "bbox": [317.34849, 383.72335999999996, 354.48237, 395.80794000000003], "text": "(9,515)"}, {"flags": 0, "span_num": 283, "line_num": 0, "block_num": 0, "bbox": [411.76718, 383.93799, 431.08538, 395.80794000000003], "text": "383"}, {"flags": 0, "span_num": 284, "line_num": 0, "block_num": 0, "bbox": [482.80339, 383.93799, 511.78067999999996, 395.80794000000003], "text": "4,424"}, {"flags": 0, "span_num": 285, "line_num": 0, "block_num": 0, "bbox": [563.48582, 383.93799, 592.4631, 395.80794000000003], "text": "2,131"}, {"flags": 0, "span_num": 286, "line_num": 0, "block_num": 0, "bbox": [644.1682, 383.93799, 673.14534, 395.80794000000003], "text": "1,302"}, {"flags": 0, "span_num": 287, "line_num": 0, "block_num": 0, "bbox": [39.29227, 397.82668, 79.00187, 409.69663], "text": "Year-end"}, {"flags": 0, "span_num": 288, "line_num": 0, "block_num": 0, "bbox": [82.75819, 397.82668, 134.0587, 409.69663], "text": "identi\ufb01able"}, {"flags": 0, "span_num": 289, "line_num": 0, "block_num": 0, "bbox": [137.81502, 397.82668, 169.58268, 409.69663], "text": "assets"}, {"flags": 0, "span_num": 290, "line_num": 0, "block_num": 0, "bbox": [308.55981, 397.61206000000004, 350.4159, 409.69663], "text": "203,894"}, {"flags": 0, "span_num": 291, "line_num": 0, "block_num": 0, "bbox": [389.24112, 397.82668, 431.09721, 409.69663], "text": "202,485"}, {"flags": 0, "span_num": 292, "line_num": 0, "block_num": 0, "bbox": [469.92355, 397.82668, 511.77964, 409.69663], "text": "161,919"}, {"flags": 0, "span_num": 293, "line_num": 0, "block_num": 0, "bbox": [550.60597, 397.82668, 592.46206, 409.69663], "text": "161,929"}, {"flags": 0, "span_num": 294, "line_num": 0, "block_num": 0, "bbox": [631.2884, 397.82668, 673.14426, 409.69663], "text": "138,613"}, {"flags": 0, "span_num": 295, "line_num": 0, "block_num": 0, "bbox": [29.19099, 417.39707999999996, 55.59251999999999, 429.26703], "text": "Asset"}, {"flags": 0, "span_num": 296, "line_num": 0, "block_num": 0, "bbox": [59.34883000000001, 417.39707999999996, 120.52305000000001, 429.26703], "text": "Management"}, {"flags": 0, "span_num": 297, "line_num": 0, "block_num": 0, "bbox": [124.27938, 417.39707999999996, 177.29702, 429.26703], "text": "operations:"}, {"flags": 0, "span_num": 298, "line_num": 0, "block_num": 0, "bbox": [39.29225, 431.28578000000005, 91.2367, 443.15572999999995], "text": "Investment"}, {"flags": 0, "span_num": 299, "line_num": 0, "block_num": 0, "bbox": [94.99302, 431.28578000000005, 128.90716, 443.15572999999995], "text": "income"}, {"flags": 0, "span_num": 300, "line_num": 0, "block_num": 0, "bbox": [132.66348, 431.28578000000005, 154.13029, 443.15572999999995], "text": "from"}, {"flags": 0, "span_num": 301, "line_num": 0, "block_num": 0, "bbox": [157.88661, 431.28578000000005, 221.31566, 443.15572999999995], "text": "spread-based"}, {"flags": 0, "span_num": 302, "line_num": 0, "block_num": 0, "bbox": [225.07198, 431.28578000000005, 266.07052, 443.15572999999995], "text": "products"}, {"flags": 0, "span_num": 303, "line_num": 0, "block_num": 0, "bbox": [49.393519999999995, 445.17448, 66.77988, 457.04443000000003], "text": "and"}, {"flags": 0, "span_num": 304, "line_num": 0, "block_num": 0, "bbox": [70.53621, 445.17448, 134.93013, 457.04443000000003], "text": "management,"}, {"flags": 0, "span_num": 305, "line_num": 0, "block_num": 0, "bbox": [138.68645, 445.17448, 177.86264, 457.04443000000003], "text": "advisory"}, {"flags": 0, "span_num": 306, "line_num": 0, "block_num": 0, "bbox": [181.61896, 445.17448, 199.00531, 457.04443000000003], "text": "and"}, {"flags": 0, "span_num": 307, "line_num": 0, "block_num": 0, "bbox": [202.76163, 445.17448, 244.40302000000003, 457.04443000000003], "text": "incentive"}, {"flags": 0, "span_num": 308, "line_num": 0, "block_num": 0, "bbox": [248.15934, 445.17448, 268.55074, 457.04443000000003], "text": "fees"}, {"flags": 0, "span_num": 309, "line_num": 0, "block_num": 0, "bbox": [321.43857, 444.95984999999996, 350.41586, 457.04443000000003], "text": "6,625"}, {"flags": 0, "span_num": 310, "line_num": 0, "block_num": 0, "bbox": [402.11988, 445.17448, 431.09717, 457.04443000000003], "text": "4,668"}, {"flags": 0, "span_num": 311, "line_num": 0, "block_num": 0, "bbox": [482.80227, 445.17448, 511.77955999999995, 457.04443000000003], "text": "4,500"}, {"flags": 0, "span_num": 312, "line_num": 0, "block_num": 0, "bbox": [563.48466, 445.17448, 592.46195, 457.04443000000003], "text": "4,179"}, {"flags": 0, "span_num": 313, "line_num": 0, "block_num": 0, "bbox": [644.16705, 445.17448, 673.14418, 457.04443000000003], "text": "3,379"}, {"flags": 0, "span_num": 314, "line_num": 0, "block_num": 0, "bbox": [39.29116, 459.06317, 55.604290000000006, 470.93312000000003], "text": "Net"}, {"flags": 0, "span_num": 315, "line_num": 0, "block_num": 0, "bbox": [59.360600000000005, 459.06317, 95.74319, 470.93312000000003], "text": "realized"}, {"flags": 0, "span_num": 316, "line_num": 0, "block_num": 0, "bbox": [99.49951, 459.06317, 130.62325, 470.93312000000003], "text": "capital"}, {"flags": 0, "span_num": 317, "line_num": 0, "block_num": 0, "bbox": [134.37957, 459.06317, 159.49319, 470.93312000000003], "text": "gains"}, {"flags": 0, "span_num": 318, "line_num": 0, "block_num": 0, "bbox": [163.24951, 459.06317, 200.59798, 470.93312000000003], "text": "(losses)"}, {"flags": 0, "span_num": 319, "line_num": 0, "block_num": 0, "bbox": [317.34633, 458.84855000000005, 354.48021, 470.93312000000003], "text": "(1,000)"}, {"flags": 0, "span_num": 320, "line_num": 0, "block_num": 0, "bbox": [408.55821, 459.06317, 434.30287, 470.93312000000003], "text": "(125)"}, {"flags": 0, "span_num": 321, "line_num": 0, "block_num": 0, "bbox": [498.88680999999997, 459.06317, 511.76561000000004, 470.93312000000003], "text": "82"}, {"flags": 0, "span_num": 322, "line_num": 0, "block_num": 0, "bbox": [579.5692, 459.06317, 592.448, 470.93312000000003], "text": "60"}, {"flags": 0, "span_num": 323, "line_num": 0, "block_num": 0, "bbox": [650.60433, 459.06317, 676.34907, 470.93312000000003], "text": "(754)"}, {"flags": 0, "span_num": 324, "line_num": 0, "block_num": 0, "bbox": [39.29008, 472.95191, 84.36585, 484.82186], "text": "Operating"}, {"flags": 0, "span_num": 325, "line_num": 0, "block_num": 0, "bbox": [88.12217, 472.95191, 122.03630999999999, 484.82186], "text": "income"}, {"flags": 0, "span_num": 326, "line_num": 0, "block_num": 0, "bbox": [321.43642, 472.73720000000003, 350.4137, 484.82186], "text": "1,164"}, {"flags": 0, "span_num": 327, "line_num": 0, "block_num": 0, "bbox": [402.11773, 472.95191, 431.09501, 484.82186], "text": "1,538"}, {"flags": 0, "span_num": 328, "line_num": 0, "block_num": 0, "bbox": [482.80011, 472.95191, 511.77739999999994, 484.82186], "text": "1,963"}, {"flags": 0, "span_num": 329, "line_num": 0, "block_num": 0, "bbox": [563.4825, 472.95191, 592.45979, 484.82186], "text": "1,947"}, {"flags": 0, "span_num": 330, "line_num": 0, "block_num": 0, "bbox": [653.81114, 472.95191, 673.12923, 484.82186], "text": "521"}, {"flags": 0, "span_num": 331, "line_num": 0, "block_num": 0, "bbox": [39.289, 486.84064, 78.99859, 498.71059], "text": "Year-end"}, {"flags": 0, "span_num": 332, "line_num": 0, "block_num": 0, "bbox": [82.75491, 486.84064, 134.05542, 498.71059], "text": "identi\ufb01able"}, {"flags": 0, "span_num": 333, "line_num": 0, "block_num": 0, "bbox": [137.81174, 486.84064, 169.57941, 498.71059], "text": "assets"}, {"flags": 0, "span_num": 334, "line_num": 0, "block_num": 0, "bbox": [314.99594, 486.62594, 350.41263, 498.71059], "text": "77,274"}, {"flags": 0, "span_num": 335, "line_num": 0, "block_num": 0, "bbox": [395.67832, 486.84064, 431.09501, 498.71059], "text": "78,275"}, {"flags": 0, "span_num": 336, "line_num": 0, "block_num": 0, "bbox": [476.36075, 486.84064, 511.77743999999996, 498.71059], "text": "69,584"}, {"flags": 0, "span_num": 337, "line_num": 0, "block_num": 0, "bbox": [557.04318, 486.84064, 592.45987, 498.71059], "text": "68,503"}, {"flags": 0, "span_num": 338, "line_num": 0, "block_num": 0, "bbox": [637.72561, 486.84064, 673.1421, 498.71059], "text": "56,047"}, {"flags": 0, "span_num": 339, "line_num": 0, "block_num": 0, "bbox": [29.1888, 506.41103999999996, 54.73173, 518.28099], "text": "Other"}, {"flags": 0, "span_num": 340, "line_num": 0, "block_num": 0, "bbox": [58.48804, 506.41103999999996, 111.50573, 518.28099], "text": "operations:"}, {"flags": 0, "span_num": 341, "line_num": 0, "block_num": 0, "bbox": [39.92112, 520.2997, 56.234260000000006, 532.16965], "text": "Net"}, {"flags": 0, "span_num": 342, "line_num": 0, "block_num": 0, "bbox": [59.990570000000005, 520.2997, 96.26582, 532.16965], "text": "realized"}, {"flags": 0, "span_num": 343, "line_num": 0, "block_num": 0, "bbox": [100.02214, 520.2997, 131.14588, 532.16965], "text": "capital"}, {"flags": 0, "span_num": 344, "line_num": 0, "block_num": 0, "bbox": [134.9022, 520.2997, 160.01583, 532.16965], "text": "gains"}, {"flags": 0, "span_num": 345, "line_num": 0, "block_num": 0, "bbox": [163.77215, 520.2997, 201.12061, 532.16965], "text": "(losses)"}, {"flags": 0, "span_num": 346, "line_num": 0, "block_num": 0, "bbox": [337.52203, 520.085, 350.40083, 532.16965], "text": "12"}, {"flags": 0, "span_num": 347, "line_num": 0, "block_num": 0, "bbox": [411.76394, 520.2997, 431.07783, 532.16965], "text": "217"}, {"flags": 0, "span_num": 348, "line_num": 0, "block_num": 0, "bbox": [495.6746, 520.2997, 514.98633, 532.16965], "text": "(71)"}, {"flags": 0, "span_num": 349, "line_num": 0, "block_num": 0, "bbox": [569.92298, 520.2997, 595.67196, 532.16965], "text": "(244)"}, {"flags": 0, "span_num": 350, "line_num": 0, "block_num": 0, "bbox": [650.60857, 520.2997, 676.35762, 532.16965], "text": "(134)"}, {"flags": 0, "span_num": 351, "line_num": 0, "block_num": 0, "bbox": [39.92008, 534.18836, 51.0817, 546.05831], "text": "All"}, {"flags": 0, "span_num": 352, "line_num": 0, "block_num": 0, "bbox": [54.83801, 532.8546, 84.93056, 546.05831], "text": "other(i)"}, {"flags": 0, "span_num": 353, "line_num": 0, "block_num": 0, "bbox": [317.34849, 533.97581, 354.48237, 546.06046], "text": "(1,430)"}, {"flags": 0, "span_num": 354, "line_num": 0, "block_num": 0, "bbox": [408.56036, 534.19051, 434.31366, 546.06046], "text": "(984)"}, {"flags": 0, "span_num": 355, "line_num": 0, "block_num": 0, "bbox": [479.57943, 534.19051, 514.98969, 546.06046], "text": "(2,383)"}, {"flags": 0, "span_num": 356, "line_num": 0, "block_num": 0, "bbox": [569.92634, 534.19051, 595.67963, 546.06046], "text": "(134)"}, {"flags": 0, "span_num": 357, "line_num": 0, "block_num": 0, "bbox": [640.94428, 534.19051, 676.35431, 546.06046], "text": "(1,254)"}, {"flags": 0, "span_num": 358, "line_num": 0, "block_num": 0, "bbox": [29.192030000000003, 553.76091, 93.80062, 565.63086], "text": "Consolidated:"}, {"flags": 0, "span_num": 359, "line_num": 0, "block_num": 0, "bbox": [39.2933, 567.64965, 61.401880000000006, 579.5196], "text": "Total"}, {"flags": 0, "span_num": 360, "line_num": 0, "block_num": 0, "bbox": [65.1582, 566.31419, 121.20581999999999, 579.5196], "text": "revenues(j)(k)"}, {"flags": 0, "span_num": 361, "line_num": 0, "block_num": 0, "bbox": [308.56062, 567.43533, 350.41671, 579.51998], "text": "110,064"}, {"flags": 0, "span_num": 362, "line_num": 0, "block_num": 0, "bbox": [389.24193, 567.65003, 431.09802, 579.51998], "text": "113,387"}, {"flags": 0, "span_num": 363, "line_num": 0, "block_num": 0, "bbox": [469.92435, 567.65003, 511.78045, 579.51998], "text": "108,781"}, {"flags": 0, "span_num": 364, "line_num": 0, "block_num": 0, "bbox": [557.04618, 567.65003, 592.46287, 579.51998], "text": "97,823"}, {"flags": 0, "span_num": 365, "line_num": 0, "block_num": 0, "bbox": [637.72861, 567.65003, 673.14511, 579.51998], "text": "79,601"}, {"flags": 0, "span_num": 366, "line_num": 0, "block_num": 0, "bbox": [39.29197, 581.53869, 84.36774, 593.40864], "text": "Operating"}, {"flags": 0, "span_num": 367, "line_num": 0, "block_num": 0, "bbox": [88.12406, 580.20308, 143.28916, 593.40864], "text": "income(b)(j)(k)"}, {"flags": 0, "span_num": 368, "line_num": 0, "block_num": 0, "bbox": [321.43938, 581.32422, 350.41667, 593.40887], "text": "8,943"}, {"flags": 0, "span_num": 369, "line_num": 0, "block_num": 0, "bbox": [395.68237, 581.53892, 431.09906, 593.40887], "text": "21,687"}, {"flags": 0, "span_num": 370, "line_num": 0, "block_num": 0, "bbox": [476.3648, 581.53892, 511.78148999999996, 593.40887], "text": "15,213"}, {"flags": 0, "span_num": 371, "line_num": 0, "block_num": 0, "bbox": [557.04722, 581.53892, 592.46391, 593.40887], "text": "14,845"}, {"flags": 0, "span_num": 372, "line_num": 0, "block_num": 0, "bbox": [637.72961, 581.53892, 673.14611, 593.40887], "text": "11,907"}, {"flags": 0, "span_num": 373, "line_num": 0, "block_num": 0, "bbox": [39.29304, 595.42758, 79.00264, 607.29753], "text": "Year-end"}, {"flags": 0, "span_num": 374, "line_num": 0, "block_num": 0, "bbox": [82.75896, 595.42758, 103.79431, 607.29753], "text": "total"}, {"flags": 0, "span_num": 375, "line_num": 0, "block_num": 0, "bbox": [107.55063, 595.42758, 139.3183, 607.29753], "text": "assets"}, {"flags": 0, "span_num": 376, "line_num": 0, "block_num": 0, "bbox": [298.88863, 595.21288, 350.4038, 607.29753], "text": "1,060,505"}, {"flags": 0, "span_num": 377, "line_num": 0, "block_num": 0, "bbox": [389.24193, 595.42758, 431.09802, 607.29753], "text": "979,410"}, {"flags": 0, "span_num": 378, "line_num": 0, "block_num": 0, "bbox": [469.92328, 595.42758, 511.77937, 607.29753], "text": "853,048"}, {"flags": 0, "span_num": 379, "line_num": 0, "block_num": 0, "bbox": [550.6057, 595.42758, 592.46179, 607.29753], "text": "801,007"}, {"flags": 0, "span_num": 380, "line_num": 0, "block_num": 0, "bbox": [631.28813, 595.42758, 673.14403, 607.29753], "text": "675,602"}, {"flags": 0, "span_num": 381, "line_num": 0, "block_num": 0, "bbox": [29.191920000000003, 616.15256, 39.98737, 626.62602], "text": "(a)"}, {"flags": 0, "span_num": 382, "line_num": 0, "block_num": 0, "bbox": [44.70991, 616.15256, 75.10765, 626.62602], "text": "Certain"}, {"flags": 0, "span_num": 383, "line_num": 0, "block_num": 0, "bbox": [78.42204, 616.15256, 145.56223, 626.62602], "text": "reclassi\ufb01cations"}, {"flags": 0, "span_num": 384, "line_num": 0, "block_num": 0, "bbox": [148.87662, 616.15256, 168.38421, 626.62602], "text": "have"}, {"flags": 0, "span_num": 385, "line_num": 0, "block_num": 0, "bbox": [171.69861, 616.15256, 192.15317, 626.62602], "text": "been"}, {"flags": 0, "span_num": 386, "line_num": 0, "block_num": 0, "bbox": [195.46756, 616.15256, 218.57362, 626.62602], "text": "made"}, {"flags": 0, "span_num": 387, "line_num": 0, "block_num": 0, "bbox": [221.88802, 616.15256, 230.03195, 626.62602], "text": "to"}, {"flags": 0, "span_num": 388, "line_num": 0, "block_num": 0, "bbox": [233.34635, 616.15256, 251.90695, 626.62602], "text": "prior"}, {"flags": 0, "span_num": 389, "line_num": 0, "block_num": 0, "bbox": [255.22134, 616.15256, 280.97893, 626.62602], "text": "period"}, {"flags": 0, "span_num": 390, "line_num": 0, "block_num": 0, "bbox": [284.29333, 616.15256, 320.46756, 626.62602], "text": "amounts"}, {"flags": 0, "span_num": 391, "line_num": 0, "block_num": 0, "bbox": [323.78195, 616.15256, 331.92587, 626.62602], "text": "to"}, {"flags": 0, "span_num": 392, "line_num": 0, "block_num": 0, "bbox": [335.24026, 616.15256, 369.04704, 626.62602], "text": "conform"}, {"flags": 0, "span_num": 393, "line_num": 0, "block_num": 0, "bbox": [372.36143, 616.15256, 380.50535, 626.62602], "text": "to"}, {"flags": 0, "span_num": 394, "line_num": 0, "block_num": 0, "bbox": [383.81974, 616.15256, 397.07728, 626.62602], "text": "the"}, {"flags": 0, "span_num": 395, "line_num": 0, "block_num": 0, "bbox": [400.39167, 616.15256, 429.74769, 626.62602], "text": "current"}, {"flags": 0, "span_num": 396, "line_num": 0, "block_num": 0, "bbox": [433.06209, 616.15256, 458.81958, 626.62602], "text": "period"}, {"flags": 0, "span_num": 397, "line_num": 0, "block_num": 0, "bbox": [462.13397, 616.15256, 517.15277, 626.62602], "text": "presentation."}]