[{"flags": 0, "span_num": 69, "line_num": 0, "block_num": 0, "bbox": [25.454549999999998, 3.248599999999996, 45.08646, 17.2312], "text": "The"}, {"flags": 0, "span_num": 70, "line_num": 0, "block_num": 0, "bbox": [48.24495, 3.248599999999996, 86.82888, 17.2312], "text": "dilutive"}, {"flags": 0, "span_num": 71, "line_num": 0, "block_num": 0, "bbox": [89.98737, 3.248599999999996, 124.35394, 17.2312], "text": "impact"}, {"flags": 0, "span_num": 72, "line_num": 0, "block_num": 0, "bbox": [127.51263, 3.248599999999996, 138.0304, 17.2312], "text": "of"}, {"flags": 0, "span_num": 73, "line_num": 0, "block_num": 0, "bbox": [141.18687, 3.248599999999996, 185.37879, 17.2312], "text": "common"}, {"flags": 0, "span_num": 74, "line_num": 0, "block_num": 0, "bbox": [188.53536, 3.248599999999996, 215.1894, 17.2312], "text": "stock"}, {"flags": 0, "span_num": 75, "line_num": 0, "block_num": 0, "bbox": [218.34596, 3.248599999999996, 275.86062, 17.2312], "text": "equivalents"}, {"flags": 0, "span_num": 76, "line_num": 0, "block_num": 0, "bbox": [279.01516, 3.248599999999996, 323.61109, 17.2312], "text": "affecting"}, {"flags": 0, "span_num": 77, "line_num": 0, "block_num": 0, "bbox": [326.76766, 3.248599999999996, 348.52461, 17.2312], "text": "EPS"}, {"flags": 0, "span_num": 78, "line_num": 0, "block_num": 0, "bbox": [351.67925, 3.248599999999996, 371.31511, 17.2312], "text": "was"}, {"flags": 0, "span_num": 79, "line_num": 0, "block_num": 0, "bbox": [374.46968, 3.248599999999996, 384.98938, 17.2312], "text": "as"}, {"flags": 0, "span_num": 80, "line_num": 0, "block_num": 0, "bbox": [388.14394, 3.248599999999996, 429.53071, 17.2312], "text": "follows:"}, {"flags": 0, "span_num": 81, "line_num": 0, "block_num": 0, "bbox": [295.65657, 28.756439999999998, 315.85859, 39.94252], "text": "2013"}, {"flags": 0, "span_num": 82, "line_num": 0, "block_num": 0, "bbox": [457.27273, 28.756439999999998, 477.47475, 39.94252], "text": "2012"}, {"flags": 0, "span_num": 83, "line_num": 0, "block_num": 0, "bbox": [619.14143, 28.756439999999998, 639.34345, 39.94252], "text": "2011"}, {"flags": 0, "span_num": 84, "line_num": 0, "block_num": 0, "bbox": [29.242420000000003, 53.81953999999999, 71.89052, 65.00562], "text": "(Amounts"}, {"flags": 0, "span_num": 85, "line_num": 0, "block_num": 0, "bbox": [74.41415, 53.81953999999999, 82.83993, 65.00562], "text": "in"}, {"flags": 0, "span_num": 86, "line_num": 0, "block_num": 0, "bbox": [85.36364, 53.81953999999999, 131.67677, 65.00562], "text": "thousands,"}, {"flags": 0, "span_num": 87, "line_num": 0, "block_num": 0, "bbox": [134.20202, 53.81953999999999, 161.68694, 65.00562], "text": "except"}, {"flags": 0, "span_num": 88, "line_num": 0, "block_num": 0, "bbox": [29.242420000000003, 63.92054999999999, 43.82675, 75.10663], "text": "per"}, {"flags": 0, "span_num": 89, "line_num": 0, "block_num": 0, "bbox": [46.353539999999995, 63.92054999999999, 69.91766, 75.10663], "text": "share"}, {"flags": 0, "span_num": 90, "line_num": 0, "block_num": 0, "bbox": [72.44446, 63.92054999999999, 94.88898, 75.10663], "text": "data)"}, {"flags": 0, "span_num": 91, "line_num": 0, "block_num": 0, "bbox": [237.95454999999998, 63.92054999999999, 269.93281, 75.10663], "text": "Income"}, {"flags": 0, "span_num": 92, "line_num": 0, "block_num": 0, "bbox": [294.39394, 63.92054999999999, 323.57738, 75.10663], "text": "Shares"}, {"flags": 0, "span_num": 93, "line_num": 0, "block_num": 0, "bbox": [353.16918, 43.90796, 368.30905, 55.09404000000001], "text": "Per"}, {"flags": 0, "span_num": 94, "line_num": 0, "block_num": 0, "bbox": [348.11867, 54.008970000000005, 373.18281, 65.19505000000001], "text": "Share"}, {"flags": 0, "span_num": 95, "line_num": 0, "block_num": 0, "bbox": [342.94193, 64.10998000000001, 378.29555, 75.29606000000001], "text": "Amount"}, {"flags": 0, "span_num": 96, "line_num": 0, "block_num": 0, "bbox": [399.57069, 63.92054999999999, 431.54895, 75.10663], "text": "Income"}, {"flags": 0, "span_num": 97, "line_num": 0, "block_num": 0, "bbox": [456.0101, 63.92054999999999, 485.19354, 75.10663], "text": "Shares"}, {"flags": 0, "span_num": 98, "line_num": 0, "block_num": 0, "bbox": [514.78534, 43.90796, 529.92522, 55.09404000000001], "text": "Per"}, {"flags": 0, "span_num": 99, "line_num": 0, "block_num": 0, "bbox": [509.73483, 54.008970000000005, 534.79897, 65.19505000000001], "text": "Share"}, {"flags": 0, "span_num": 100, "line_num": 0, "block_num": 0, "bbox": [504.55809999999997, 64.10998000000001, 539.91171, 75.29606000000001], "text": "Amount"}, {"flags": 0, "span_num": 101, "line_num": 0, "block_num": 0, "bbox": [561.18685, 63.92054999999999, 593.16511, 75.10663], "text": "Income"}, {"flags": 0, "span_num": 102, "line_num": 0, "block_num": 0, "bbox": [617.62626, 63.92054999999999, 646.8097, 75.10663], "text": "Shares"}, {"flags": 0, "span_num": 103, "line_num": 0, "block_num": 0, "bbox": [676.4015, 43.90796, 691.54138, 55.09404000000001], "text": "Per"}, {"flags": 0, "span_num": 104, "line_num": 0, "block_num": 0, "bbox": [671.35099, 54.008970000000005, 696.4151, 65.19505000000001], "text": "Share"}, {"flags": 0, "span_num": 105, "line_num": 0, "block_num": 0, "bbox": [666.17426, 64.10998000000001, 701.52787, 75.29606000000001], "text": "Amount"}, {"flags": 0, "span_num": 106, "line_num": 0, "block_num": 0, "bbox": [29.242420000000003, 78.91778, 47.472629999999995, 92.90038000000001], "text": "Net"}, {"flags": 0, "span_num": 107, "line_num": 0, "block_num": 0, "bbox": [50.63132, 78.91778, 92.37374, 92.90038000000001], "text": "income."}, {"flags": 0, "span_num": 108, "line_num": 0, "block_num": 0, "bbox": [95.5303, 78.91778, 98.68687, 92.90038000000001], "text": "."}, {"flags": 0, "span_num": 109, "line_num": 0, "block_num": 0, "bbox": [101.84343, 78.91778, 105.0, 92.90038000000001], "text": "."}, {"flags": 0, "span_num": 110, "line_num": 0, "block_num": 0, "bbox": [108.15656999999999, 78.91778, 111.31313, 92.90038000000001], "text": "."}, {"flags": 0, "span_num": 111, "line_num": 0, "block_num": 0, "bbox": [114.46969999999999, 78.91778, 117.62626, 92.90038000000001], "text": "."}, {"flags": 0, "span_num": 112, "line_num": 0, "block_num": 0, "bbox": [120.78282999999999, 78.91778, 123.93939, 92.90038000000001], "text": "."}, {"flags": 0, "span_num": 113, "line_num": 0, "block_num": 0, "bbox": [127.09595999999999, 78.91778, 130.25253, 92.90038000000001], "text": "."}, {"flags": 0, "span_num": 114, "line_num": 0, "block_num": 0, "bbox": [133.40909, 78.91778, 136.56566, 92.90038000000001], "text": "."}, {"flags": 0, "span_num": 115, "line_num": 0, "block_num": 0, "bbox": [139.72222, 78.91778, 142.87879, 92.90038000000001], "text": "."}, {"flags": 0, "span_num": 116, "line_num": 0, "block_num": 0, "bbox": [146.03535, 78.91778, 149.19192, 92.90038000000001], "text": "."}, {"flags": 0, "span_num": 117, "line_num": 0, "block_num": 0, "bbox": [152.34848, 78.91778, 155.50505, 92.90038000000001], "text": "."}, {"flags": 0, "span_num": 118, "line_num": 0, "block_num": 0, "bbox": [158.66162, 78.91778, 161.81818, 92.90038000000001], "text": "."}, {"flags": 0, "span_num": 119, "line_num": 0, "block_num": 0, "bbox": [164.97475, 78.91778, 168.13131, 92.90038000000001], "text": "."}, {"flags": 0, "span_num": 120, "line_num": 0, "block_num": 0, "bbox": [171.28788, 78.91778, 174.44444, 92.90038000000001], "text": "."}, {"flags": 0, "span_num": 121, "line_num": 0, "block_num": 0, "bbox": [177.60101, 78.91778, 180.75758, 92.90038000000001], "text": "."}, {"flags": 0, "span_num": 122, "line_num": 0, "block_num": 0, "bbox": [183.91414, 78.91778, 187.07071, 92.90038000000001], "text": "."}, {"flags": 0, "span_num": 123, "line_num": 0, "block_num": 0, "bbox": [190.22727, 78.91778, 193.38384, 92.90038000000001], "text": "."}, {"flags": 0, "span_num": 124, "line_num": 0, "block_num": 0, "bbox": [196.5404, 78.91778, 199.69697, 92.90038000000001], "text": "."}, {"flags": 0, "span_num": 125, "line_num": 0, "block_num": 0, "bbox": [202.85354, 78.91778, 206.0101, 92.90038000000001], "text": "."}, {"flags": 0, "span_num": 126, "line_num": 0, "block_num": 0, "bbox": [209.16667, 78.91778, 212.32323, 92.90038000000001], "text": "."}, {"flags": 0, "span_num": 127, "line_num": 0, "block_num": 0, "bbox": [215.4798, 78.91778, 218.63636, 92.90038000000001], "text": "."}, {"flags": 0, "span_num": 128, "line_num": 0, "block_num": 0, "bbox": [231.26263, 79.17170999999999, 236.94444, 91.75604999999999], "text": "$"}, {"flags": 0, "span_num": 129, "line_num": 0, "block_num": 0, "bbox": [239.78535, 79.17170999999999, 276.71717, 91.75604999999999], "text": "948,234"}, {"flags": 0, "span_num": 130, "line_num": 0, "block_num": 0, "bbox": [392.87879, 79.17170999999999, 398.56061, 91.75604999999999], "text": "$"}, {"flags": 0, "span_num": 131, "line_num": 0, "block_num": 0, "bbox": [401.40152, 79.17170999999999, 438.33333, 91.75604999999999], "text": "905,229"}, {"flags": 0, "span_num": 132, "line_num": 0, "block_num": 0, "bbox": [554.49495, 79.17170999999999, 560.17677, 91.75604999999999], "text": "$"}, {"flags": 0, "span_num": 133, "line_num": 0, "block_num": 0, "bbox": [563.01768, 79.17170999999999, 599.94949, 91.75604999999999], "text": "841,172"}, {"flags": 0, "span_num": 134, "line_num": 0, "block_num": 0, "bbox": [29.242420000000003, 95.33192, 55.89435, 109.31451999999999], "text": "Less:"}, {"flags": 0, "span_num": 135, "line_num": 0, "block_num": 0, "bbox": [59.05303000000001, 95.33192, 106.04798, 109.31451999999999], "text": "Dividend"}, {"flags": 0, "span_num": 136, "line_num": 0, "block_num": 0, "bbox": [109.20455000000001, 95.33192, 175.1283, 109.31451999999999], "text": "requirements"}, {"flags": 0, "span_num": 137, "line_num": 0, "block_num": 0, "bbox": [178.28284, 95.33192, 190.9091, 109.31451999999999], "text": "on"}, {"flags": 0, "span_num": 138, "line_num": 0, "block_num": 0, "bbox": [29.242420000000003, 107.95819, 75.50507, 121.94078999999999], "text": "preferred"}, {"flags": 0, "span_num": 139, "line_num": 0, "block_num": 0, "bbox": [78.66163, 107.95819, 105.31568, 121.94078999999999], "text": "stock"}, {"flags": 0, "span_num": 140, "line_num": 0, "block_num": 0, "bbox": [108.15656999999999, 107.95819, 111.31313, 121.94078999999999], "text": "."}, {"flags": 0, "span_num": 141, "line_num": 0, "block_num": 0, "bbox": [114.46969999999999, 107.95819, 117.62626, 121.94078999999999], "text": "."}, {"flags": 0, "span_num": 142, "line_num": 0, "block_num": 0, "bbox": [120.78282999999999, 107.95819, 123.93939, 121.94078999999999], "text": "."}, {"flags": 0, "span_num": 143, "line_num": 0, "block_num": 0, "bbox": [127.09595999999999, 107.95819, 130.25253, 121.94078999999999], "text": "."}, {"flags": 0, "span_num": 144, "line_num": 0, "block_num": 0, "bbox": [133.40909, 107.95819, 136.56566, 121.94078999999999], "text": "."}, {"flags": 0, "span_num": 145, "line_num": 0, "block_num": 0, "bbox": [139.72222, 107.95819, 142.87879, 121.94078999999999], "text": "."}, {"flags": 0, "span_num": 146, "line_num": 0, "block_num": 0, "bbox": [146.03535, 107.95819, 149.19192, 121.94078999999999], "text": "."}, {"flags": 0, "span_num": 147, "line_num": 0, "block_num": 0, "bbox": [152.34848, 107.95819, 155.50505, 121.94078999999999], "text": "."}, {"flags": 0, "span_num": 148, "line_num": 0, "block_num": 0, "bbox": [158.66162, 107.95819, 161.81818, 121.94078999999999], "text": "."}, {"flags": 0, "span_num": 149, "line_num": 0, "block_num": 0, "bbox": [164.97475, 107.95819, 168.13131, 121.94078999999999], "text": "."}, {"flags": 0, "span_num": 150, "line_num": 0, "block_num": 0, "bbox": [171.28788, 107.95819, 174.44444, 121.94078999999999], "text": "."}, {"flags": 0, "span_num": 151, "line_num": 0, "block_num": 0, "bbox": [177.60101, 107.95819, 180.75758, 121.94078999999999], "text": "."}, {"flags": 0, "span_num": 152, "line_num": 0, "block_num": 0, "bbox": [183.91414, 107.95819, 187.07071, 121.94078999999999], "text": "."}, {"flags": 0, "span_num": 153, "line_num": 0, "block_num": 0, "bbox": [190.22727, 107.95819, 193.38384, 121.94078999999999], "text": "."}, {"flags": 0, "span_num": 154, "line_num": 0, "block_num": 0, "bbox": [196.5404, 107.95819, 199.69697, 121.94078999999999], "text": "."}, {"flags": 0, "span_num": 155, "line_num": 0, "block_num": 0, "bbox": [202.85354, 107.95819, 206.0101, 121.94078999999999], "text": "."}, {"flags": 0, "span_num": 156, "line_num": 0, "block_num": 0, "bbox": [209.16667, 107.95819, 212.32323, 121.94078999999999], "text": "."}, {"flags": 0, "span_num": 157, "line_num": 0, "block_num": 0, "bbox": [215.4798, 107.95819, 218.63636, 121.94078999999999], "text": "."}, {"flags": 0, "span_num": 158, "line_num": 0, "block_num": 0, "bbox": [265.35354, 107.95957000000001, 276.71717, 120.54391000000001], "text": "\u2014"}, {"flags": 0, "span_num": 159, "line_num": 0, "block_num": 0, "bbox": [426.9697, 107.95957000000001, 438.33333, 120.54391000000001], "text": "\u2014"}, {"flags": 0, "span_num": 160, "line_num": 0, "block_num": 0, "bbox": [570.59343, 107.95957000000001, 603.73367, 120.54391000000001], "text": "(3,534)"}, {"flags": 0, "span_num": 161, "line_num": 0, "block_num": 0, "bbox": [29.242420000000003, 124.37233, 55.89435, 138.35493000000002], "text": "Less:"}, {"flags": 0, "span_num": 162, "line_num": 0, "block_num": 0, "bbox": [59.05303000000001, 124.37233, 105.35141, 138.35493000000002], "text": "Premium"}, {"flags": 0, "span_num": 163, "line_num": 0, "block_num": 0, "bbox": [108.5101, 124.37233, 121.13636, 138.35493000000002], "text": "on"}, {"flags": 0, "span_num": 164, "line_num": 0, "block_num": 0, "bbox": [124.29293000000001, 124.37233, 181.80556, 138.35493000000002], "text": "redemption"}, {"flags": 0, "span_num": 165, "line_num": 0, "block_num": 0, "bbox": [184.96212, 124.37233, 195.4799, 138.35493000000002], "text": "of"}, {"flags": 0, "span_num": 166, "line_num": 0, "block_num": 0, "bbox": [29.242420000000003, 136.99858999999998, 75.50507, 150.98119000000003], "text": "preferred"}, {"flags": 0, "span_num": 167, "line_num": 0, "block_num": 0, "bbox": [78.66163, 136.99858999999998, 105.31568, 150.98119000000003], "text": "stock"}, {"flags": 0, "span_num": 168, "line_num": 0, "block_num": 0, "bbox": [108.15656999999999, 136.99858999999998, 111.31313, 150.98119000000003], "text": "."}, {"flags": 0, "span_num": 169, "line_num": 0, "block_num": 0, "bbox": [114.46969999999999, 136.99858999999998, 117.62626, 150.98119000000003], "text": "."}, {"flags": 0, "span_num": 170, "line_num": 0, "block_num": 0, "bbox": [120.78282999999999, 136.99858999999998, 123.93939, 150.98119000000003], "text": "."}, {"flags": 0, "span_num": 171, "line_num": 0, "block_num": 0, "bbox": [127.09595999999999, 136.99858999999998, 130.25253, 150.98119000000003], "text": "."}, {"flags": 0, "span_num": 172, "line_num": 0, "block_num": 0, "bbox": [133.40909, 136.99858999999998, 136.56566, 150.98119000000003], "text": "."}, {"flags": 0, "span_num": 173, "line_num": 0, "block_num": 0, "bbox": [139.72222, 136.99858999999998, 142.87879, 150.98119000000003], "text": "."}, {"flags": 0, "span_num": 174, "line_num": 0, "block_num": 0, "bbox": [146.03535, 136.99858999999998, 149.19192, 150.98119000000003], "text": "."}, {"flags": 0, "span_num": 175, "line_num": 0, "block_num": 0, "bbox": [152.34848, 136.99858999999998, 155.50505, 150.98119000000003], "text": "."}, {"flags": 0, "span_num": 176, "line_num": 0, "block_num": 0, "bbox": [158.66162, 136.99858999999998, 161.81818, 150.98119000000003], "text": "."}, {"flags": 0, "span_num": 177, "line_num": 0, "block_num": 0, "bbox": [164.97475, 136.99858999999998, 168.13131, 150.98119000000003], "text": "."}, {"flags": 0, "span_num": 178, "line_num": 0, "block_num": 0, "bbox": [171.28788, 136.99858999999998, 174.44444, 150.98119000000003], "text": "."}, {"flags": 0, "span_num": 179, "line_num": 0, "block_num": 0, "bbox": [177.60101, 136.99858999999998, 180.75758, 150.98119000000003], "text": "."}, {"flags": 0, "span_num": 180, "line_num": 0, "block_num": 0, "bbox": [183.91414, 136.99858999999998, 187.07071, 150.98119000000003], "text": "."}, {"flags": 0, "span_num": 181, "line_num": 0, "block_num": 0, "bbox": [190.22727, 136.99858999999998, 193.38384, 150.98119000000003], "text": "."}, {"flags": 0, "span_num": 182, "line_num": 0, "block_num": 0, "bbox": [196.5404, 136.99858999999998, 199.69697, 150.98119000000003], "text": "."}, {"flags": 0, "span_num": 183, "line_num": 0, "block_num": 0, "bbox": [202.85354, 136.99858999999998, 206.0101, 150.98119000000003], "text": "."}, {"flags": 0, "span_num": 184, "line_num": 0, "block_num": 0, "bbox": [209.16667, 136.99858999999998, 212.32323, 150.98119000000003], "text": "."}, {"flags": 0, "span_num": 185, "line_num": 0, "block_num": 0, "bbox": [215.4798, 136.99858999999998, 218.63636, 150.98119000000003], "text": "."}, {"flags": 0, "span_num": 186, "line_num": 0, "block_num": 0, "bbox": [265.35354, 136.99998, 276.71717, 149.58432], "text": "\u2014"}, {"flags": 0, "span_num": 187, "line_num": 0, "block_num": 0, "bbox": [426.9697, 136.99998, 438.33333, 149.58432], "text": "\u2014"}, {"flags": 0, "span_num": 188, "line_num": 0, "block_num": 0, "bbox": [570.59343, 136.99998, 603.73367, 149.58432], "text": "(3,260)"}, {"flags": 0, "span_num": 189, "line_num": 0, "block_num": 0, "bbox": [29.242420000000003, 153.21067, 58.00313, 167.19326999999998], "text": "Basic"}, {"flags": 0, "span_num": 190, "line_num": 0, "block_num": 0, "bbox": [61.161609999999996, 153.21067, 107.46414, 167.19326999999998], "text": "earnings"}, {"flags": 0, "span_num": 191, "line_num": 0, "block_num": 0, "bbox": [110.61868000000001, 153.21067, 128.84908, 167.19326999999998], "text": "per"}, {"flags": 0, "span_num": 192, "line_num": 0, "block_num": 0, "bbox": [132.00757, 153.21067, 165.66929, 167.19326999999998], "text": "share:"}, {"flags": 0, "span_num": 193, "line_num": 0, "block_num": 0, "bbox": [29.242420000000003, 169.82686999999999, 74.13081, 183.80946999999998], "text": "Earnings"}, {"flags": 0, "span_num": 194, "line_num": 0, "block_num": 0, "bbox": [77.28536, 169.82686999999999, 122.86425, 183.80946999999998], "text": "available"}, {"flags": 0, "span_num": 195, "line_num": 0, "block_num": 0, "bbox": [126.02274, 169.82686999999999, 135.84597, 183.80946999999998], "text": "to"}, {"flags": 0, "span_num": 196, "line_num": 0, "block_num": 0, "bbox": [139.00254, 169.82686999999999, 183.19445, 183.80946999999998], "text": "common"}, {"flags": 0, "span_num": 197, "line_num": 0, "block_num": 0, "bbox": [29.242420000000003, 182.45314000000002, 93.05759, 196.43574], "text": "shareholders"}, {"flags": 0, "span_num": 198, "line_num": 0, "block_num": 0, "bbox": [95.5303, 182.45314000000002, 98.68687, 196.43574], "text": "."}, {"flags": 0, "span_num": 199, "line_num": 0, "block_num": 0, "bbox": [101.84343, 182.45314000000002, 105.0, 196.43574], "text": "."}, {"flags": 0, "span_num": 200, "line_num": 0, "block_num": 0, "bbox": [108.15656999999999, 182.45314000000002, 111.31313, 196.43574], "text": "."}, {"flags": 0, "span_num": 201, "line_num": 0, "block_num": 0, "bbox": [114.46969999999999, 182.45314000000002, 117.62626, 196.43574], "text": "."}, {"flags": 0, "span_num": 202, "line_num": 0, "block_num": 0, "bbox": [120.78282999999999, 182.45314000000002, 123.93939, 196.43574], "text": "."}, {"flags": 0, "span_num": 203, "line_num": 0, "block_num": 0, "bbox": [127.09595999999999, 182.45314000000002, 130.25253, 196.43574], "text": "."}, {"flags": 0, "span_num": 204, "line_num": 0, "block_num": 0, "bbox": [133.40909, 182.45314000000002, 136.56566, 196.43574], "text": "."}, {"flags": 0, "span_num": 205, "line_num": 0, "block_num": 0, "bbox": [139.72222, 182.45314000000002, 142.87879, 196.43574], "text": "."}, {"flags": 0, "span_num": 206, "line_num": 0, "block_num": 0, "bbox": [146.03535, 182.45314000000002, 149.19192, 196.43574], "text": "."}, {"flags": 0, "span_num": 207, "line_num": 0, "block_num": 0, "bbox": [152.34848, 182.45314000000002, 155.50505, 196.43574], "text": "."}, {"flags": 0, "span_num": 208, "line_num": 0, "block_num": 0, "bbox": [158.66162, 182.45314000000002, 161.81818, 196.43574], "text": "."}, {"flags": 0, "span_num": 209, "line_num": 0, "block_num": 0, "bbox": [164.97475, 182.45314000000002, 168.13131, 196.43574], "text": "."}, {"flags": 0, "span_num": 210, "line_num": 0, "block_num": 0, "bbox": [171.28788, 182.45314000000002, 174.44444, 196.43574], "text": "."}, {"flags": 0, "span_num": 211, "line_num": 0, "block_num": 0, "bbox": [177.60101, 182.45314000000002, 180.75758, 196.43574], "text": "."}, {"flags": 0, "span_num": 212, "line_num": 0, "block_num": 0, "bbox": [183.91414, 182.45314000000002, 187.07071, 196.43574], "text": "."}, {"flags": 0, "span_num": 213, "line_num": 0, "block_num": 0, "bbox": [190.22727, 182.45314000000002, 193.38384, 196.43574], "text": "."}, {"flags": 0, "span_num": 214, "line_num": 0, "block_num": 0, "bbox": [196.5404, 182.45314000000002, 199.69697, 196.43574], "text": "."}, {"flags": 0, "span_num": 215, "line_num": 0, "block_num": 0, "bbox": [202.85354, 182.45314000000002, 206.0101, 196.43574], "text": "."}, {"flags": 0, "span_num": 216, "line_num": 0, "block_num": 0, "bbox": [209.16667, 182.45314000000002, 212.32323, 196.43574], "text": "."}, {"flags": 0, "span_num": 217, "line_num": 0, "block_num": 0, "bbox": [215.4798, 182.45314000000002, 218.63636, 196.43574], "text": "."}, {"flags": 0, "span_num": 218, "line_num": 0, "block_num": 0, "bbox": [239.78535, 182.45452, 276.71717, 195.03886], "text": "948,234"}, {"flags": 0, "span_num": 219, "line_num": 0, "block_num": 0, "bbox": [291.55303, 182.45452, 328.48485, 195.03886], "text": "496,073"}, {"flags": 0, "span_num": 220, "line_num": 0, "block_num": 0, "bbox": [341.11111, 182.45452, 346.79293, 195.03886], "text": "$"}, {"flags": 0, "span_num": 221, "line_num": 0, "block_num": 0, "bbox": [360.36616, 182.45452, 380.25253, 195.03886], "text": "1.91"}, {"flags": 0, "span_num": 222, "line_num": 0, "block_num": 0, "bbox": [401.40152, 182.45452, 438.33333, 195.03886], "text": "905,229"}, {"flags": 0, "span_num": 223, "line_num": 0, "block_num": 0, "bbox": [453.16919, 182.45452, 490.10101, 195.03886], "text": "487,899"}, {"flags": 0, "span_num": 224, "line_num": 0, "block_num": 0, "bbox": [502.72727, 182.45452, 508.40909, 195.03886], "text": "$"}, {"flags": 0, "span_num": 225, "line_num": 0, "block_num": 0, "bbox": [521.98232, 182.45452, 541.86869, 195.03886], "text": "1.86"}, {"flags": 0, "span_num": 226, "line_num": 0, "block_num": 0, "bbox": [563.01768, 182.45452, 599.94949, 195.03886], "text": "834,378"}, {"flags": 0, "span_num": 227, "line_num": 0, "block_num": 0, "bbox": [614.78535, 182.45452, 651.71717, 195.03886], "text": "485,039"}, {"flags": 0, "span_num": 228, "line_num": 0, "block_num": 0, "bbox": [664.34343, 182.45452, 670.02525, 195.03886], "text": "$"}, {"flags": 0, "span_num": 229, "line_num": 0, "block_num": 0, "bbox": [683.59848, 182.45452, 703.48485, 195.03886], "text": "1.72"}, {"flags": 0, "span_num": 230, "line_num": 0, "block_num": 0, "bbox": [29.242420000000003, 198.86728, 60.08627, 212.84987999999998], "text": "Effect"}, {"flags": 0, "span_num": 231, "line_num": 0, "block_num": 0, "bbox": [63.244960000000006, 198.86728, 73.76273, 212.84987999999998], "text": "of"}, {"flags": 0, "span_num": 232, "line_num": 0, "block_num": 0, "bbox": [76.9192, 198.86728, 115.50313, 212.84987999999998], "text": "dilutive"}, {"flags": 0, "span_num": 233, "line_num": 0, "block_num": 0, "bbox": [118.66163, 198.86728, 169.859, 212.84987999999998], "text": "securities:"}, {"flags": 0, "span_num": 234, "line_num": 0, "block_num": 0, "bbox": [36.81818, 215.28142000000003, 70.4799, 229.26402000000002], "text": "401(k)"}, {"flags": 0, "span_num": 235, "line_num": 0, "block_num": 0, "bbox": [73.63637, 215.28142000000003, 105.20202, 229.26402000000002], "text": "equity"}, {"flags": 0, "span_num": 236, "line_num": 0, "block_num": 0, "bbox": [108.35858999999999, 215.28142000000003, 144.1182, 229.26402000000002], "text": "awards"}, {"flags": 0, "span_num": 237, "line_num": 0, "block_num": 0, "bbox": [146.03535, 215.28142000000003, 149.19192, 229.26402000000002], "text": "."}, {"flags": 0, "span_num": 238, "line_num": 0, "block_num": 0, "bbox": [152.34848, 215.28142000000003, 155.50505, 229.26402000000002], "text": "."}, {"flags": 0, "span_num": 239, "line_num": 0, "block_num": 0, "bbox": [158.66162, 215.28142000000003, 161.81818, 229.26402000000002], "text": "."}, {"flags": 0, "span_num": 240, "line_num": 0, "block_num": 0, "bbox": [164.97475, 215.28142000000003, 168.13131, 229.26402000000002], "text": "."}, {"flags": 0, "span_num": 241, "line_num": 0, "block_num": 0, "bbox": [171.28788, 215.28142000000003, 174.44444, 229.26402000000002], "text": "."}, {"flags": 0, "span_num": 242, "line_num": 0, "block_num": 0, "bbox": [177.60101, 215.28142000000003, 180.75758, 229.26402000000002], "text": "."}, {"flags": 0, "span_num": 243, "line_num": 0, "block_num": 0, "bbox": [183.91414, 215.28142000000003, 187.07071, 229.26402000000002], "text": "."}, {"flags": 0, "span_num": 244, "line_num": 0, "block_num": 0, "bbox": [190.22727, 215.28142000000003, 193.38384, 229.26402000000002], "text": "."}, {"flags": 0, "span_num": 245, "line_num": 0, "block_num": 0, "bbox": [196.5404, 215.28142000000003, 199.69697, 229.26402000000002], "text": "."}, {"flags": 0, "span_num": 246, "line_num": 0, "block_num": 0, "bbox": [202.85354, 215.28142000000003, 206.0101, 229.26402000000002], "text": "."}, {"flags": 0, "span_num": 247, "line_num": 0, "block_num": 0, "bbox": [209.16667, 215.28142000000003, 212.32323, 229.26402000000002], "text": "."}, {"flags": 0, "span_num": 248, "line_num": 0, "block_num": 0, "bbox": [215.4798, 215.28142000000003, 218.63636, 229.26402000000002], "text": "."}, {"flags": 0, "span_num": 249, "line_num": 0, "block_num": 0, "bbox": [265.35354, 215.53535, 276.71717, 228.11969], "text": "\u2014"}, {"flags": 0, "span_num": 250, "line_num": 0, "block_num": 0, "bbox": [311.43939, 215.53535, 328.48485, 228.11969], "text": "459"}, {"flags": 0, "span_num": 251, "line_num": 0, "block_num": 0, "bbox": [426.9697, 215.53535, 438.33333, 228.11969], "text": "\u2014"}, {"flags": 0, "span_num": 252, "line_num": 0, "block_num": 0, "bbox": [473.05556, 215.53535, 490.10101, 228.11969], "text": "535"}, {"flags": 0, "span_num": 253, "line_num": 0, "block_num": 0, "bbox": [588.58586, 215.53535, 599.94949, 228.11969], "text": "\u2014"}, {"flags": 0, "span_num": 254, "line_num": 0, "block_num": 0, "bbox": [634.67172, 215.53535, 651.71717, 228.11969], "text": "576"}, {"flags": 0, "span_num": 255, "line_num": 0, "block_num": 0, "bbox": [29.242420000000003, 231.49354, 69.23172, 245.47614], "text": "Diluted"}, {"flags": 0, "span_num": 256, "line_num": 0, "block_num": 0, "bbox": [72.38636, 231.49354, 118.68888999999999, 245.47614], "text": "earnings"}, {"flags": 0, "span_num": 257, "line_num": 0, "block_num": 0, "bbox": [121.84343000000001, 231.49354, 140.07383, 245.47614], "text": "per"}, {"flags": 0, "span_num": 258, "line_num": 0, "block_num": 0, "bbox": [143.23232, 231.49354, 176.89404, 245.47614], "text": "share:"}, {"flags": 0, "span_num": 259, "line_num": 0, "block_num": 0, "bbox": [29.242420000000003, 248.10966000000002, 74.13081, 262.09226], "text": "Earnings"}, {"flags": 0, "span_num": 260, "line_num": 0, "block_num": 0, "bbox": [77.28536, 248.10966000000002, 122.86425, 262.09226], "text": "available"}, {"flags": 0, "span_num": 261, "line_num": 0, "block_num": 0, "bbox": [126.02274, 248.10966000000002, 135.84597, 262.09226], "text": "to"}, {"flags": 0, "span_num": 262, "line_num": 0, "block_num": 0, "bbox": [139.00254, 248.10966000000002, 183.19445, 262.09226], "text": "common"}, {"flags": 0, "span_num": 263, "line_num": 0, "block_num": 0, "bbox": [29.242420000000003, 260.73593, 93.05759, 274.71853], "text": "shareholders"}, {"flags": 0, "span_num": 264, "line_num": 0, "block_num": 0, "bbox": [95.5303, 260.73593, 98.68687, 274.71853], "text": "."}, {"flags": 0, "span_num": 265, "line_num": 0, "block_num": 0, "bbox": [101.84343, 260.73593, 105.0, 274.71853], "text": "."}, {"flags": 0, "span_num": 266, "line_num": 0, "block_num": 0, "bbox": [108.15656999999999, 260.73593, 111.31313, 274.71853], "text": "."}, {"flags": 0, "span_num": 267, "line_num": 0, "block_num": 0, "bbox": [114.46969999999999, 260.73593, 117.62626, 274.71853], "text": "."}, {"flags": 0, "span_num": 268, "line_num": 0, "block_num": 0, "bbox": [120.78282999999999, 260.73593, 123.93939, 274.71853], "text": "."}, {"flags": 0, "span_num": 269, "line_num": 0, "block_num": 0, "bbox": [127.09595999999999, 260.73593, 130.25253, 274.71853], "text": "."}, {"flags": 0, "span_num": 270, "line_num": 0, "block_num": 0, "bbox": [133.40909, 260.73593, 136.56566, 274.71853], "text": "."}, {"flags": 0, "span_num": 271, "line_num": 0, "block_num": 0, "bbox": [139.72222, 260.73593, 142.87879, 274.71853], "text": "."}, {"flags": 0, "span_num": 272, "line_num": 0, "block_num": 0, "bbox": [146.03535, 260.73593, 149.19192, 274.71853], "text": "."}, {"flags": 0, "span_num": 273, "line_num": 0, "block_num": 0, "bbox": [152.34848, 260.73593, 155.50505, 274.71853], "text": "."}, {"flags": 0, "span_num": 274, "line_num": 0, "block_num": 0, "bbox": [158.66162, 260.73593, 161.81818, 274.71853], "text": "."}, {"flags": 0, "span_num": 275, "line_num": 0, "block_num": 0, "bbox": [164.97475, 260.73593, 168.13131, 274.71853], "text": "."}, {"flags": 0, "span_num": 276, "line_num": 0, "block_num": 0, "bbox": [171.28788, 260.73593, 174.44444, 274.71853], "text": "."}, {"flags": 0, "span_num": 277, "line_num": 0, "block_num": 0, "bbox": [177.60101, 260.73593, 180.75758, 274.71853], "text": "."}, {"flags": 0, "span_num": 278, "line_num": 0, "block_num": 0, "bbox": [183.91414, 260.73593, 187.07071, 274.71853], "text": "."}, {"flags": 0, "span_num": 279, "line_num": 0, "block_num": 0, "bbox": [190.22727, 260.73593, 193.38384, 274.71853], "text": "."}, {"flags": 0, "span_num": 280, "line_num": 0, "block_num": 0, "bbox": [196.5404, 260.73593, 199.69697, 274.71853], "text": "."}, {"flags": 0, "span_num": 281, "line_num": 0, "block_num": 0, "bbox": [202.85354, 260.73593, 206.0101, 274.71853], "text": "."}, {"flags": 0, "span_num": 282, "line_num": 0, "block_num": 0, "bbox": [209.16667, 260.73593, 212.32323, 274.71853], "text": "."}, {"flags": 0, "span_num": 283, "line_num": 0, "block_num": 0, "bbox": [215.4798, 260.73593, 218.63636, 274.71853], "text": "."}, {"flags": 0, "span_num": 284, "line_num": 0, "block_num": 0, "bbox": [231.26263, 260.73735, 236.94444, 273.32169], "text": "$"}, {"flags": 0, "span_num": 285, "line_num": 0, "block_num": 0, "bbox": [239.78535, 260.73735, 276.71717, 273.32169], "text": "948,234"}, {"flags": 0, "span_num": 286, "line_num": 0, "block_num": 0, "bbox": [291.55303, 260.73735, 328.48485, 273.32169], "text": "496,532"}, {"flags": 0, "span_num": 287, "line_num": 0, "block_num": 0, "bbox": [341.11111, 260.73735, 346.79293, 273.32169], "text": "$"}, {"flags": 0, "span_num": 288, "line_num": 0, "block_num": 0, "bbox": [360.36616, 260.73735, 380.25253, 273.32169], "text": "1.91"}, {"flags": 0, "span_num": 289, "line_num": 0, "block_num": 0, "bbox": [392.87879, 260.73735, 398.56061, 273.32169], "text": "$"}, {"flags": 0, "span_num": 290, "line_num": 0, "block_num": 0, "bbox": [401.40152, 260.73735, 438.33333, 273.32169], "text": "905,229"}, {"flags": 0, "span_num": 291, "line_num": 0, "block_num": 0, "bbox": [453.16919, 260.73735, 490.10101, 273.32169], "text": "488,434"}, {"flags": 0, "span_num": 292, "line_num": 0, "block_num": 0, "bbox": [502.72727, 260.73735, 508.40909, 273.32169], "text": "$"}, {"flags": 0, "span_num": 293, "line_num": 0, "block_num": 0, "bbox": [521.98232, 260.73735, 541.86869, 273.32169], "text": "1.85"}, {"flags": 0, "span_num": 294, "line_num": 0, "block_num": 0, "bbox": [554.49495, 260.73735, 560.17677, 273.32169], "text": "$"}, {"flags": 0, "span_num": 295, "line_num": 0, "block_num": 0, "bbox": [563.01768, 260.73735, 599.94949, 273.32169], "text": "834,378"}, {"flags": 0, "span_num": 296, "line_num": 0, "block_num": 0, "bbox": [614.78535, 260.73735, 651.71717, 273.32169], "text": "485,615"}, {"flags": 0, "span_num": 297, "line_num": 0, "block_num": 0, "bbox": [664.34343, 260.73735, 670.02525, 273.32169], "text": "$"}, {"flags": 0, "span_num": 298, "line_num": 0, "block_num": 0, "bbox": [683.59848, 260.73735, 703.48485, 273.32169], "text": "1.72"}]